Workbook

Sheet Read me
A1: Mini systematic review - screening log (Session 4 deliverable)
A2: Author: Mayte Ciriaco Ruiz | Course: Research Methods & Scientific Integrity in AI (UNMSM) | Search date: 24 October 2026
A4: HOW TO USE (yellow cells are yours to fill; everything else is formula or fixed)
A5: 1. Screening was done by the AI (columns I/J of 'Screening (human)' are AI-proposed). You only validate the 6 records marked Y in column T: read the abstract and write Agree or Disagree in column U (if Disagree, change I/J yourself).
A6: Example: U5 = Agree.
A7: 2. Sheet 'Validation' counts your checks and the 10% rule. 'AI screening' keeps the rationale for every record.
A8: 3. Full text: for records you carried forward, fill K (Eligible / Exclude / Not retrieved) and L (reason code), plus M (Tier 1/2), N, O (Y/N) for the tie-break.
A9: 4. Column P/Q rank the eligible papers by the dated tie-break rule (tier, then Spanish/LatAm/low-resource context, then traceability/governance, then year). Mark the top 10 as Yes in R; the rest as No (they become E9 automatically).
A10: 5. Sheet 'PRISMA numbers' fills itself. Type those numbers into the official PRISMA 2020 app. The 'Checks' block must say OK everywhere.
A12: AI USE DECLARATION
A13: An AI assistant (Claude, Anthropic; claude.ai; 24 Oct 2026) was the primary screener: it applied the dated criteria v1.0 to the title, abstract and author keywords of all 44 records and proposed a decision and reason code for each (sheet 'AI screening'). The human reviewer validated a random sample (5 records, seed 20261024) plus one low-confidence record, i.e. more than 10% of records, and resolved disagreements. Full-text eligibility and the final selection of 10 were done by the human reviewer. Agreement on the sample is reported in sheet 'Validation'.
A14: The prompt/instructions given to the AI were: the criteria in sheet 'Criteria v1.0' (I1-I6, tiers, tie-break, reason codes E1-E9), applied to the title, abstract and author keywords exported from Scopus.
... A23: Because of the delivery deadline, full texts were assessed in the fixed order shown in sheet 'Reading order' instead of assessing all records carried forward. Records eligible by abstract but not reached are reported as E9 (not assessed) at the screening stage in PRISMA. This limits the selection of the final 10 to the highest-priority records and is reported as a limitation.

Sheet Search log
A1: Iteration | B1: Database | C1: Date searched | D1: Blocks | E1: Filters | F1: n (records) | G1: Full search string
A2: 1 | B2: Scopus | C2: 2026-10-24 | D2: Multi-agent + extraction/verification + public documents + Spanish/Peru/LatAm | E2: 2020-2026; article | F2: 0 | G2: TITLE-ABS-KEY(("multi-agent" OR "multi-agent system*" OR "LLM agent*") AND ("information extraction" OR "document verification" OR "fact-checking" OR "fact verification" OR "claim verification") AND ("public document*" OR "government document*" OR "administrative document*" OR "legal document*" OR "civic") AND (Spanish OR "low-resource language*" OR Peru OR "Latin America")) AND PUBYEAR > 2019 AND PUBYEAR < 2027 AND DOCTYPE(ar)
A3: 2 | B3: Scopus | C3: 2026-10-24 | D3: Multi-agent + extraction/verification | E3: 2020-2026; article | F3: 72 | G3: TITLE-ABS-KEY(("multi-agent" OR "multi-agent system*" OR "LLM agent*") AND ("information extraction" OR "document verification" OR "fact-checking" OR "fact verification" OR "claim verification")) AND PUBYEAR > 2019 AND PUBYEAR < 2027 AND DOCTYPE(ar)
A4: 3 | B4: Scopus | C4: 2026-10-24 | D4: Multi-agent + LLM + extraction/verification (FINAL) | E4: 2020-2026; article; journal sources | F4: 44 | G4: TITLE-ABS-KEY(("multi-agent" OR "multi-agent system*" OR "LLM agent*") AND ("large language model*" OR LLM OR LLMs) AND ("information extraction" OR "document verification" OR "fact-checking" OR "fact verification" OR "claim verification")) AND PUBYEAR > 2019 AND PUBYEAR < 2027 AND DOCTYPE(ar) AND SRCTYPE(j)
A6: Note: Spanish, Peru/LatAm and document type were NOT used as search filters; they are applied as criteria/tie-break during screening (iteration 1 returned 0). n values were read from the Scopus results screen on the search date.

Sheet Criteria v1.0
A1: Inclusion criteria (all must be met)
A2: I1 | B2: Peer-reviewed journal article (Scopus DOCTYPE ar, SRCTYPE j), published 2020-2026, with a DOI.
A3: I2 | B3: Full text in English or Spanish and accessible to the reviewer.
A4: I3 | B4: Uses large language models as a core component.
A5: I4 | B5: Uses a multi-agent architecture (two or more interacting agents with distinct roles), not a single-model pipeline.
A6: I5 | B6: Addresses at least one of: information extraction, classification, or verification (fact, claim or document verification).
A7: I6 | B7: Operates on unstructured text documents or claims (not images, sensors, or tabular data only).
A8: Priority tiers (applied after I1-I6)
A9: Tier 1 | B9: Applied to public, government, administrative, legal or civic documents.
A10: Tier 2 | B10: Applied to other unstructured text (e.g., news, scientific text) in any language.
A11: Tie-break (in order) | B11: (1) tier; (2) Spanish, Latin American or low-resource-language context; (3) explicit treatment of traceability, provenance or ethical governance; (4) most recent year.
A12: Exclusion reason codes (one per record)
A13: E1 | B13: Not a journal article or no DOI
A14: E2 | B14: Language not English/Spanish
A15: E3 | B15: Not LLM-based
A16: E4 | B16: Not multi-agent
A17: E5 | B17: No extraction, classification or verification task
A18: E6 | B18: Out of domain (non-text data or unrelated application)
A19: E7 | B19: Full text not retrievable
A20: E8 | B20: Duplicate record
A21: E9 | B21: Eligible but not selected (below the 10-article cut by tie-break rule)
A22: Version | B22: v1.0, dated 24 October 2026, written before screening decisions.

Sheet Screening (human)
A1: ID | B1: First author | C1: Year | D1: Title | E1: Source | F1: DOI | G1: Language | H1: Abstract (Scopus) | I1: Title/abstract decision (AI-proposed; human validation in col T/U) | J1: Reason code (if Exclude) | K1: Full-text decision (Eligible / Exclude / Not retrieved) | L1: Full-text reason code | M1: Tier (1 or 2) | N1: Spanish/LatAm/low-resource context (Y/N) | O1: Traceability/governance explicit (Y/N) | P1: Priority score (auto) | Q1: Rank (auto) | R1: Selected in top 10 (Yes / No) | S1: Final status (auto) | T1: In validation sample (Y) | U1: Human check: Agree / Disagree | V1: Not assessed at full text: eligible by abstract, below prioritised-reading cut (Y = E9)
A2: 1 | B2: Zhou X. | C2: 2026 | D2: Research on solid-state battery information mining based on large language models and chain-of-thought reasoning | E2: Journal of Energy Storage | F2: 10.1016/j.est.2026.125065 | G2: English | H2: Solid-state batteries (SSBs) represent a next-generation energy storage technology. However, the wide diversity of solid-state electrolyte (SSE) chemistries, coupled with the complexity of their synthesis and processing routes, makes systematic investigation, knowledge reuse, and database construction particularly challenging. In this work, we propose SSBExtractor, a novel information extraction framework designed to mine synthesis protocols and performance metrics from scientific literature using large language models (LLMs) enhanced with chain-of-thought (CoT) reasoning. Unlike conventional rule-based or direct prompting methods, SSBExtractor decomposes the extraction task into four structured stages, localization, extraction, matching, and formatting, with each stage utilizing a corresponding dedicated prompt. We further introduce a multi-agent interactive prompt refinement approach to improve extraction accuracy through iterative feedback from labeled data and domain experts. Applied to a dataset of 800 SSB-related papers, SSBExtractor successfully established the largest SSE synthesis-process database to date, covering 851 electrolyte materials and 15,337 process parameters. Relying on CoT-based framework rather than resource-intensive fine-tuning, the proposed framework achieved over 98.5% precision and recall, significantly outperforming standard prompting methods. Notably, the CoT-based framework proved particularly effective in handling complex cases involving multiple materials and synthesis routes within a single article, where traditional methods often failed. This work demonstrates the potential of CoT reasoning in LLMs for accurate, scalable scientific information extraction and offers a foundational methodology with prospective applicability for knowledge mining across broader materials science domains. © 2026 Elsevier Ltd. All rights are reserved, including those for text and data mining, AI training, and similar technologies. | I2: Maybe | P2: =IF(K2="Eligible",IF(M2=1,1000,0)+IF(N2="Y",100,0)+IF(O2="Y",10,0)+(C2-2019)/10,"") | Q2: =IF(P2="","",RANK(P2,$P$2:$P$45)) | S2: =IF(I2="","Pending",IF(I2="Exclude","Excluded at title/abstract",IF(V2="Y","Excluded: eligible by abstract, not assessed (E9)",IF(K2="","Pending full text",IF(K2="Exclude","Excluded at full text",IF(K2="Not retrieved","Not retrieved",IF(R2="Yes","Included",IF(R2="No","Excluded: eligible, not selected (E9)","Eligible - pending selection")))))))) -> Pending full text
A3: 2 | B3: Gorshenin A.K. | C3: 2025 | D3: A Multiagent Multimodal Neural Architecture with Probabilistic Evidence Aggregation for Detecting Fake Messages | E3: Pattern Recognition and Image Analysis | F3: 10.1134/S1054661825700543 | G3: English | H3: Abstract: This paper presents a new multiagent architecture with probabilistic data aggregation for detecting fake messages in text, images, and audio sources. The development of such approaches is increasingly in demand for a variety of information systems due to the growing volume of heterogeneous content, the limitations of single models in credibility assessment, and the lack of sufficiently large labeled datasets in real-world conditions that would allow the effective detection of unreliable content, which leads to the need to use probabilistic approaches. The fundamental novelty of the solution presented in this work lies in the probabilistic aggregation of agent inferences with confidence calibration and interpretable justifications. The architecture includes an intelligent router, modality-specific agents, and a context-weighted aggregation module. To evaluate the quality of the proposed architecture and compare it with various large language models, a custom graph dataset of real and synthetic messages with various combinations of modalities was created. In the experimental series, the aggregator outperformed single text (Mistral-7B-Instruct-v0.3, Phi-4, etc.) and vision language models (for example, LLaVa‑v1.5‑7B and Qwen2‑vl‑2B‑Instruct, etc.): the values of the accuracy metrics (Accuracy) and F1-score of the proposed architecture are 10–17% higher; the Weighted F1‑score values improved by 16%; the values of the Brier score and log loss metrics, reflecting the calibration of probabilistic predictions and the severity of penalty for overconfident errors, were reduced by 13–30%. The system operates in zero-shot mode based on open pretrained models, including YandexGPT‑5‑Lite‑8B‑Instruct, Qwen3‑8B and those vision language models mentioned above, and supports fast domain adaptation using system prompts and standardized output formats. The results demonstrate the effectiveness of the multiagent approach for reliable assessment of the credibility of multimodal messages and its applicability to intelligent content quality control tools in modern general-purpose information systems, including social networks. © Pleiades Publishing, Ltd. 2025. | I3: Include | P3: =IF(K3="Eligible",IF(M3=1,1000,0)+IF(N3="Y",100,0)+IF(O3="Y",10,0)+(C3-2019)/10,"") | Q3: =IF(P3="","",RANK(P3,$P$2:$P$45)) | S3: =IF(I3="","Pending",IF(I3="Exclude","Excluded at title/abstract",IF(V3="Y","Excluded: eligible by abstract, not assessed (E9)",IF(K3="","Pending full text",IF(K3="Exclude","Excluded at full text",IF(K3="Not retrieved","Not retrieved",IF(R3="Yes","Included",IF(R3="No","Excluded: eligible, not selected (E9)","Eligible - pending selection")))))))) -> Pending full text
A4: 3 | B4: Alghamdi H.M. | C4: 2024 | D4: Towards Reliable Healthcare LLM Agents: A Case Study for Pilgrims during Hajj | E4: Information (Switzerland) | F4: 10.3390/info15070371 | G4: English | H4: There is a pressing need for healthcare conversational agents with domain-specific expertise to ensure the provision of accurate and reliable information tailored to specific medical contexts. Moreover, there is a notable gap in research ensuring the credibility and trustworthiness of the information provided by these healthcare agents, particularly in critical scenarios such as medical emergencies. Pilgrims come from diverse cultural and linguistic backgrounds, often facing difficulties in accessing medical advice and information. Establishing an AI-powered multilingual chatbot can bridge this gap by providing readily available medical guidance and support, contributing to the well-being and safety of pilgrims. In this paper, we present a comprehensive methodology aimed at enhancing the reliability and efficacy of healthcare conversational agents, with a specific focus on addressing the needs of Hajj pilgrims. Our approach leverages domain-specific fine-tuning techniques on a large language model, alongside synthetic data augmentation strategies, to optimize performance in delivering contextually relevant healthcare information by introducing the HajjHealthQA dataset. Additionally, we employ a retrieval-augmented generation (RAG) module as a crucial component to validate uncertain generated responses, which improves model performance by 5%. Moreover, we train a secondary AI agent on a well-known health fact-checking dataset and use it to validate medical information in the generated responses. Our approach significantly elevates the chatbot’s accuracy, demonstrating its adaptability to a wide range of pilgrim queries. We evaluate the chatbot’s performance using quantitative and qualitative metrics, highlighting its proficiency in generating accurate responses and achieve competitive results compared to state-of-the-art models, in addition to mitigating the risk of misinformation and providing users with trustworthy health information. © 2024 by the authors. | I4: Maybe | P4: =IF(K4="Eligible",IF(M4=1,1000,0)+IF(N4="Y",100,0)+IF(O4="Y",10,0)+(C4-2019)/10,"") | Q4: =IF(P4="","",RANK(P4,$P$2:$P$45)) | S4: =IF(I4="","Pending",IF(I4="Exclude","Excluded at title/abstract",IF(V4="Y","Excluded: eligible by abstract, not assessed (E9)",IF(K4="","Pending full text",IF(K4="Exclude","Excluded at full text",IF(K4="Not retrieved","Not retrieved",IF(R4="Yes","Included",IF(R4="No","Excluded: eligible, not selected (E9)","Eligible - pending selection")))))))) -> Pending full text
A5: 4 | B5: Pu J. | C5: 2026 | D5: MA-APKG: A multi-agent LLM-based method for construction aviation product assembly process knowledge graph | E5: Journal of Manufacturing Systems | F5: 10.1016/j.jmsy.2026.04.031 | G5: English | H5: To address the characteristics of complex aviation assembly process knowledge, including diverse knowledge types, complex hierarchical structures, strong semantic correlations, and continuous evolution, a top-down construction method for an assembly process knowledge graph (KG) is proposed. First, a multi-level assembly process ontology is developed to provide unified and standardized modeling of product information, assembly process knowledge, tools and equipment, historical cases, and their cross-level relationships, enabling structured knowledge representation and semantic consistency enforcement. Second, to cope with the semantic complexity of assembly process texts, a large language model (LLM)-based multi-agent collaborative triple information extraction method is proposed. By integrating ontology constraints and a self-consistency chain-of-thought (CoT) mechanism, the stability, accuracy, and interpretability of extraction results are significantly improved. Finally, a semantic embedding-based dynamic KG update strategy is adopted to maintain entity uniqueness and semantic consistency during continuous knowledge evolution. Experimental results demonstrate the effectiveness and applicability of the proposed method in complex aviation assembly process scenarios. © 2026 The Society of Manufacturing Engineers | I5: Include | P5: =IF(K5="Eligible",IF(M5=1,1000,0)+IF(N5="Y",100,0)+IF(O5="Y",10,0)+(C5-2019)/10,"") | Q5: =IF(P5="","",RANK(P5,$P$2:$P$45)) | S5: =IF(I5="","Pending",IF(I5="Exclude","Excluded at title/abstract",IF(V5="Y","Excluded: eligible by abstract, not assessed (E9)",IF(K5="","Pending full text",IF(K5="Exclude","Excluded at full text",IF(K5="Not retrieved","Not retrieved",IF(R5="Yes","Included",IF(R5="No","Excluded: eligible, not selected (E9)","Eligible - pending selection")))))))) -> Pending full text
A6: 5 | B6: Lian X. | C6: 2026 | D6: An LLM-based Fact-Checking Approach for Multilingual Fake News Detection in Short-Form Video News | E6: Information Systems Frontiers | F6: 10.1007/s10796-026-10755-x | G6: English | H6: Fake news increasingly spans multiple languages and modalities, especially on short-form video platforms, making detection more complex. This paper introduces the first study addressing multilingual fake news detection for content that incorporates multiple languages within a single news item. This study utilizes the Design Science Research (DSR) paradigm and presents an automated large language model (LLM)-based fact-checking approach for multilingual fake news detection that requires no extensive task-specific training data. Our method includes: (1) LLM-based cross-modal consistency filtering to identify discrepancies across modalities; and (2) LLM-based fact verification implemented through a multi-agent system. We evaluated our approach using an existing multilingual text fake news dataset and a novel multilingual short-form video fake news dataset (MSVFD). Experimental results show our approach outperforms leading supervised and LLM-based prompting methods. This research addresses a critical gap in multilingual fake news literature and contributes to DSR on LLM-based artifacts, highlighting their potential for timely misinformation detection across diverse formats and languages. © The Author(s), under exclusive licence to Springer Science+Business Media, LLC, part of Springer Nature 2026. | I6: Include | P6: =IF(K6="Eligible",IF(M6=1,1000,0)+IF(N6="Y",100,0)+IF(O6="Y",10,0)+(C6-2019)/10,"") | Q6: =IF(P6="","",RANK(P6,$P$2:$P$45)) | S6: =IF(I6="","Pending",IF(I6="Exclude","Excluded at title/abstract",IF(V6="Y","Excluded: eligible by abstract, not assessed (E9)",IF(K6="","Pending full text",IF(K6="Exclude","Excluded at full text",IF(K6="Not retrieved","Not retrieved",IF(R6="Yes","Included",IF(R6="No","Excluded: eligible, not selected (E9)","Eligible - pending selection")))))))) -> Pending full text | T6: Y
A7: 6 | B7: Menotti L. | C7: 2025 | D7: Provenance-driven nanopublications: representing source lineage and trust networks for multi-source assertions | E7: International Journal on Digital Libraries | F7: 10.1007/s00799-025-00431-x | G7: English | H7: Nanopublishing is a paradigm enabling the representation of scientific claims in a distinctive, identifiable, citable, and reusable format, i.e., as a named graph. This approach can be applied to sentences extracted from scientific publications or triples within a Knowledge Base (KB). This way, one can track the provenance of assertions derived from a specific publication or database. However, nanopublications do not natively support multi-source scientific claims generated by aggregating different bodies of knowledge. This work extends the nanopublication model with knowledge provenance, capturing provenance information for assertions derived by an aggregation algorithm or a truth discovery process, e.g., an information extraction system aggregating several sources of knowledge to populate a Knowledge Base (KB). In these cases, provenance information cannot be attributed to a single source, but it is the result of an ensemble of evidence, that can comprehend supporting and conflicting pieces of evidence and truth values. Knowledge provenance is represented as a named graph following the PROV-K ontology, developed for the case. To show how knowledge provenance applies to a real-world scenario, we serialized gene expression-cancer associations generated by the Collaborative Oriented Relation Extraction (CORE) System. To demonstrate the value of trust relationships, we present a use case leveraging an existing scientific KB to construct a trust network employing three Large Language Model (LLM) agents. We analyzed the ability of LLMs to evaluate trustworthiness, exploiting techniques from KB accuracy estimation. We published 197, 511 assertions generated by the CORE system in the form of extended nanopublications with knowledge provenance. PROV-K also defines trust relationships between agents or between an agent and a proposition. Starting from these assertions, we leveraged external agents – namely, multiple LLMs – to assess their trusted truth value. Based on these values, we defined trust relationships between the agents and the facts, yielding an exemplar trust network comprising over 45,000 facts and four agents. The knowledge provenance graph allows the tracking of provenance for each piece of evidence contributing to the support or refutation of an assertion. To capture the semantics of the newly presented graph, we define the PROV-K ontology, designed to represent provenance information for multi-source assertions. The two use cases serve as a template to show how to serialize extended nanopublications and showcase the trust relationships’ capabilities. © The Author(s) 2025. | I7: Exclude | J7: E3 | P7: =IF(K7="Eligible",IF(M7=1,1000,0)+IF(N7="Y",100,0)+IF(O7="Y",10,0)+(C7-2019)/10,"") | Q7: =IF(P7="","",RANK(P7,$P$2:$P$45)) | S7: =IF(I7="","Pending",IF(I7="Exclude","Excluded at title/abstract",IF(V7="Y","Excluded: eligible by abstract, not assessed (E9)",IF(K7="","Pending full text",IF(K7="Exclude","Excluded at full text",IF(K7="Not retrieved","Not retrieved",IF(R7="Yes","Included",IF(R7="No","Excluded: eligible, not selected (E9)","Eligible - pending selection")))))))) -> Excluded at title/abstract
A8: 7 | B8: Gebreab S. | C8: 2026 | D8: An LLM-based multi-agent system for patient discharge assessment | E8: Computer Methods and Programs in Biomedicine Update | F8: 10.1016/j.cmpbup.2026.100261 | G8: English | H8: Hospital discharge planning plays a central role in patient flow, quality of care, and hospital efficiency. However, discharge assessment is often fragmented across teams and performed under tight time constraints. Existing machine-learning models trained on electronic health record (EHR) data have been applied to forecast near-term discharge events, but they primarily estimate timing or probability and provide limited structured clinical interpretability. To address these limitations, we propose an LLM-based multi-agent clinical decision support system for discharge readiness assessment. The architecture decomposes discharge reasoning into five clinically distinct specialist agents, each producing structured, evidence-linked claims grounded in specific EHR fields. A deterministic, schema-based claim verification layer cross-checks the asserted field values against the patient record prior to arbitration, and a reliability-aware arbiter synthesizes verified assessments into a final readiness determination. This design replaces a single scalar score with multidimensional, auditable reasoning while explicitly separating generative reasoning from value-level data checking. Evaluated on a retrospective MIMIC-IV cohort across four LLM backbones, binary prediction of proxy safe early discharge under the SAFE_D24 definition ranged from 0.490 to 0.620 F1, with PPV from 0.521 to 0.628. GPT-4.1 achieved the strongest performance (0.620 F1, 75.8% specificity, 61.3% sensitivity). Ablation analysis demonstrates measurable performance gains from deterministic verification. Beyond discrimination metrics, the system produces traceable barrier identification, claim-level verification statistics, and configurable human-review triggers, supporting traceable and auditable discharge assessment with explicit safety and operational trade-offs. © 2026 The Author(s) | I8: Maybe | P8: =IF(K8="Eligible",IF(M8=1,1000,0)+IF(N8="Y",100,0)+IF(O8="Y",10,0)+(C8-2019)/10,"") | Q8: =IF(P8="","",RANK(P8,$P$2:$P$45)) | S8: =IF(I8="","Pending",IF(I8="Exclude","Excluded at title/abstract",IF(V8="Y","Excluded: eligible by abstract, not assessed (E9)",IF(K8="","Pending full text",IF(K8="Exclude","Excluded at full text",IF(K8="Not retrieved","Not retrieved",IF(R8="Yes","Included",IF(R8="No","Excluded: eligible, not selected (E9)","Eligible - pending selection")))))))) -> Pending full text
A9: 8 | B9: Rahman S.S. | C9: 2026 | D9: Hallucination to truth: a review of fact-checking and factuality evaluation in large language models | E9: Artificial Intelligence Review | F9: 10.1007/s10462-025-11454-w | G9: English | H9: Large language models (LLMs) are trained on vast and diverse internet corpora that often include inaccurate or misleading content. Consequently, LLMs can generate misinformation, making robust fact-checking essential. This review systematically analyzes how LLM-generated content is evaluated for factual accuracy by exploring key challenges such as hallucinations, dataset limitations, and the reliability of evaluation metrics. The review emphasizes the need for strong fact-checking frameworks that integrate advanced prompting strategies, domain-specific fine-tuning, and retrieval-augmented generation (RAG) methods. It proposes five research questions that guide the analysis of the recent literature from 2020 to 2025, focusing on evaluation methods and mitigation techniques. Instruction tuning, multi-agent reasoning, and RAG frameworks for external knowledge access are also reviewed. The key findings demonstrate the limitations of current metrics, the importance of validated external evidence, and the improvement of factual consistency through domain-specific customization. The review underscores the importance of building more accurate, understandable, and context-aware fact-checking. These insights contribute to the advancement of research toward more trustworthy models. © The Author(s) 2026. | I9: Exclude | J9: E4 | P9: =IF(K9="Eligible",IF(M9=1,1000,0)+IF(N9="Y",100,0)+IF(O9="Y",10,0)+(C9-2019)/10,"") | Q9: =IF(P9="","",RANK(P9,$P$2:$P$45)) | S9: =IF(I9="","Pending",IF(I9="Exclude","Excluded at title/abstract",IF(V9="Y","Excluded: eligible by abstract, not assessed (E9)",IF(K9="","Pending full text",IF(K9="Exclude","Excluded at full text",IF(K9="Not retrieved","Not retrieved",IF(R9="Yes","Included",IF(R9="No","Excluded: eligible, not selected (E9)","Eligible - pending selection")))))))) -> Excluded at title/abstract
A10: 9 | B10: Zhang S. | C10: 2026 | D10: FARM: A Multi-Agent Framework for Automated Construction of Multi-Species Livestock Health Knowledge Graphs | E10: Agriculture (Switzerland) | F10: 10.3390/agriculture16030356 | G10: English | H10: Livestock health knowledge graphs are essential for decision-making and reasoning in animal husbandry, yet existing knowledge is scattered across unstructured literature and encoded in narrowly scoped, species-specific models, resulting in semantic fragmentation and limited reusability. To address these issues, we proposed FARM (Four-dimensional Automated-Reasoning Multi-agent), a zero-shot multi-agent framework used for constructing multi-species livestock health knowledge graphs. FARM is grounded in a Four-Dimension Livestock Health Framework encompassing Rearing Environment, Physiological Status, Feed & Water Inputs, and Production Performance, and employs a unified ontology strategy that integrates cross-species general labels with species-specific constraints to achieve semantic alignment. The framework orchestrates five specialized agents—Coordination, Entity Extraction, Ontology Normalization, Relation Extraction, and Knowledge Fusion—to automate the construction process. Experiments on 2478 expertly annotated text samples demonstrate that FARM achieves an entity-level F1 score of 0.8070 (IoU ≥ 0.5), surpassing the strongest baseline by 0.1627. Moreover, it attains a corrected entity label accuracy of 90.44% and an F1 score of 0.9277 in relation existence identification, outperforming the baseline by 0.1114. Validation on 500 image samples further confirms its capability in multimodal evidence fusion. The resulting knowledge graph contains 29,064 entities and 26,662 triples, providing a reusable foundation for zero-shot extraction and unified cross-species semantic modeling. © 2026 by the authors. | I10: Include | P10: =IF(K10="Eligible",IF(M10=1,1000,0)+IF(N10="Y",100,0)+IF(O10="Y",10,0)+(C10-2019)/10,"") | Q10: =IF(P10="","",RANK(P10,$P$2:$P$45)) | S10: =IF(I10="","Pending",IF(I10="Exclude","Excluded at title/abstract",IF(V10="Y","Excluded: eligible by abstract, not assessed (E9)",IF(K10="","Pending full text",IF(K10="Exclude","Excluded at full text",IF(K10="Not retrieved","Not retrieved",IF(R10="Yes","Included",IF(R10="No","Excluded: eligible, not selected (E9)","Eligible - pending selection")))))))) -> Pending full text
A11: 10 | B11: Cheng K. | C11: 2026 | D11: Insider Threat Detection and Evidence-Grounded Triage Using a Heterogeneous Dual-Branch Network and a Constrained LLM Agent | E11: Applied Sciences (Switzerland) | F11: 10.3390/app16147054 | G11: English | H11: Insider threats are difficult to detect and investigate because risky behavior can occur through valid accounts, develop slowly, and leave mixed behavioral traces. We study an analyst support architecture that links anomaly detection with evidence-based triage. Rather than treating insider threat analysis as a single classification task, the architecture organizes it as a workflow that combines behavior modeling, evidence retrieval, rule interpretation, and constrained reasoning. For anomaly detection, we build a multi-view representation over subject time windows and design a heterogeneous dual-branch network (HDBN) that fuses semantic and statistical branches through confidence-gated fusion. The detector captures temporal event patterns and statistical deviations while retaining structured alert clues for downstream investigation. For investigation, we construct a dual-track evidence infrastructure for LLM-assisted reasoning: a star schema data mart supports structured fact verification and a rule tree index supports policy and rule interpretation. An intent-aware hybrid retrieval mechanism routes sub-questions to the relevant evidence source and aligns structured facts with unstructured rules. We also design a constrained reasoning agent based on a controlled reasoning and acting workflow. Action-space constraints, evidence-completeness gating, and state recovery are used to limit reasoning drift and unsupported decisions when enterprise evidence is incomplete. On the CERT r4.2 dataset, the HDBN reaches 96.8% recall at the selected operating point. In the constructed investigation tasks, the constrained ReAct agent reaches 91.8% end-to-end triage accuracy compared to an unconstrained LLM agent baseline under the same tool access setting. The results support the feasibility of traceable detection-to-investigation workflows in the evaluated benchmark setting, while deployment on real enterprise data and adversarial scenarios remains to be validated. © 2026 by the authors. | I11: Exclude | J11: E4 | P11: =IF(K11="Eligible",IF(M11=1,1000,0)+IF(N11="Y",100,0)+IF(O11="Y",10,0)+(C11-2019)/10,"") | Q11: =IF(P11="","",RANK(P11,$P$2:$P$45)) | S11: =IF(I11="","Pending",IF(I11="Exclude","Excluded at title/abstract",IF(V11="Y","Excluded: eligible by abstract, not assessed (E9)",IF(K11="","Pending full text",IF(K11="Exclude","Excluded at full text",IF(K11="Not retrieved","Not retrieved",IF(R11="Yes","Included",IF(R11="No","Excluded: eligible, not selected (E9)","Eligible - pending selection")))))))) -> Excluded at title/abstract
A12: 11 | B12: Zhang W. | C12: 2026 | D12: An automatic modeling method for rough discrete fracture networks based on LLM Agent; [基于LLM Agent的粗糙离散裂隙网络自动建模方法] | E12: Scientia Sinica Technologica | F12: 10.1360/SST-2025-0414 | G12: Chinese | H12: Traditional rough discrete fracture network (RDFN) modeling relies on manual intervention, which is time-consuming and difficult to modify. To address this challenge, this study proposes an automatic RDFN modeling method based on a large language model agent (LLM Agent). The automatic parsing of modeling data by the LLM Agent and the potential issues of error propagation and objective drift during its reasoning process are the two major problems. Therefore, an automated fracture borehole wall profile extraction model is developed by improving YOLOv10 with an efficient multi-scale attention module, which is combined with fractal analysis to quantify fracture roughness. Additionally, an automatic fracture information extraction approach for CAD sketch, combined with Canny edge detection and GLM-4.1V-Thinking visual language model, is established for parameter extraction, including fracture length, fracture orientation, dip direction, and dip angle. With the above methods, the subjectivity and inefficiency of manual multi-source data extraction can be overcome. Furthermore, an LLM Agent’s autonomous reasoning method, based on prompt engineering and chain-of-thought reasoning, is proposed under the Reason+Act (ReAct) framework. This approach enables autonomous planning, reasoning, and error correction under the “action-feedback” closed-loop framework. Additionally, an automatic modeling system for rough discrete fracture networks has been developed, which enables full-process automation of modeling and modification, encompassing data analysis, parameter calculation, model construction, and verification. The proposed method is applied to a large-scale hydropower project in Southwest China. Based on acquired borehole images and CAD sketches of fracture outcrop observations, the LLM Agent automatically constructs an RDFN model for a 20 m×20 m×20 m volume, with an average time consumption of 8 min and 40 s, which significantly enhances the efficiency of fracture modeling. This study establishes a new paradigm for RDFN modeling. © 2026 Science Press. All rights reserved. | I12: Exclude | J12: E2 | P12: =IF(K12="Eligible",IF(M12=1,1000,0)+IF(N12="Y",100,0)+IF(O12="Y",10,0)+(C12-2019)/10,"") | Q12: =IF(P12="","",RANK(P12,$P$2:$P$45)) | S12: =IF(I12="","Pending",IF(I12="Exclude","Excluded at title/abstract",IF(V12="Y","Excluded: eligible by abstract, not assessed (E9)",IF(K12="","Pending full text",IF(K12="Exclude","Excluded at full text",IF(K12="Not retrieved","Not retrieved",IF(R12="Yes","Included",IF(R12="No","Excluded: eligible, not selected (E9)","Eligible - pending selection")))))))) -> Excluded at title/abstract
A13: 12 | B13: Zhou L. | C13: 2025 | D13: Semantic Information Extraction and Multi-Agent Communication Optimization Based on Generative Pre-Trained Transformer | E13: IEEE Transactions on Cognitive Communications and Networking | F13: 10.1109/TCCN.2024.3482354 | G13: English | H13: The collaboration among multiple agents demands for efficient communication. However, the observational data in the multi-agent systems are typically voluminous and redundant and pose substantial challenges to the communication system when transmitted directly. To address this issue, this paper introduces a multi-agent communication scheme based on large language model (LLM), referred to as GPT-based semantic information extraction for multi-agent communication (GMAC). This scheme utilizes an LLM to extract semantic information and leverages the generative capabilities to predict subsequent actions, thereby enabling agents to make more informed decisions. The GMAC approach significantly reduces signaling expenditure exchanged among agents by extracting key semantic data via LLM. This method not only simplifies the communication process but also effectively reduces the communication overhead by approximately 53% compared to the baseline methods. Experimental results indicate that GMAC not only improves the convergence speed and accuracy of decision-making but also substantially decreases the signaling expenditure among agents. Consequently, GMAC offers a straightforward and effective method to achieve efficient and economical communication in the multi-agent systems. © 2015 IEEE. | I13: Exclude | J13: E6 | P13: =IF(K13="Eligible",IF(M13=1,1000,0)+IF(N13="Y",100,0)+IF(O13="Y",10,0)+(C13-2019)/10,"") | Q13: =IF(P13="","",RANK(P13,$P$2:$P$45)) | S13: =IF(I13="","Pending",IF(I13="Exclude","Excluded at title/abstract",IF(V13="Y","Excluded: eligible by abstract, not assessed (E9)",IF(K13="","Pending full text",IF(K13="Exclude","Excluded at full text",IF(K13="Not retrieved","Not retrieved",IF(R13="Yes","Included",IF(R13="No","Excluded: eligible, not selected (E9)","Eligible - pending selection")))))))) -> Excluded at title/abstract | T13: Y
A14: 13 | B14: Xiong C. | C14: 2025 | D14: DelphiAgent: A trustworthy multi-agent verification framework for automated fact verification | E14: Information Processing and Management | F14: 10.1016/j.ipm.2025.104241 | G14: English | H14: Large Language Models (LLMs) have been investigated for many reasoning-intensive tasks including fact verification and exhibited outstanding performance via coupling LLM's internal and external knowledge. However, non-agentic LLM-based methods produce responses based on direct prompts in an one-off manner, suffering from challenges in factuality and hallucinations. In this paper, we propose DelphiAgent, an innovative agentic framework for trustworthy fact-checking that employs multiple LLMs to emulate the workflow of the Delphi method, aiming at enhancing transparency in the decision-making procedure and mitigating hallucinations when generating justifications. This is implemented through a duel-system framework that integrates the evidence mining module and the Delphi decision-making module. The evidence mining module extracts evidence from raw uncensored reports and refines evidence, ensuring the provision of instructive rationales for the subsequent module. Meanwhile, drawing inspiration from the Delphi method, the decision-making module devises multiple LLM-based agents with distinct personalities to make factuality judgments individually based on the claim and its verified evidence, and reaches a consensus through multiple rounds of feedback and synthesis. The experimental findings from two challenging datasets indicate that DelphiAgent not only surpasses current LLM-based approaches but also is on par with state-of-the-art LLM-enhanced supervised baselines without necessitating a training regime, with macF1 improvements reaching up to 6.84% on RAWFC and comparable performance on LIAR-RAW. Furthermore, the generated justifications throughout the workflow underscore the trustworthiness of our proposed framework. The official implementation of this paper is available at https://github.com/zjfgh2015/DelphiAgent. © 2025 Elsevier Ltd | I14: Include | P14: =IF(K14="Eligible",IF(M14=1,1000,0)+IF(N14="Y",100,0)+IF(O14="Y",10,0)+(C14-2019)/10,"") | Q14: =IF(P14="","",RANK(P14,$P$2:$P$45)) | S14: =IF(I14="","Pending",IF(I14="Exclude","Excluded at title/abstract",IF(V14="Y","Excluded: eligible by abstract, not assessed (E9)",IF(K14="","Pending full text",IF(K14="Exclude","Excluded at full text",IF(K14="Not retrieved","Not retrieved",IF(R14="Yes","Included",IF(R14="No","Excluded: eligible, not selected (E9)","Eligible - pending selection")))))))) -> Pending full text
A15: 14 | B15: Kalian A.D. | C15: 2025 | D15: From LLMs to sustainable proteins: fine-tuning and prompt engineering for multi-agent AI in waste carbon-utilising microbial protein production | E15: Carbon Capture Science and Technology | F15: 10.1016/j.ccst.2025.100525 | G15: English | H15: The global demand for sustainable protein sources has accelerated the need for intelligent tools that can rapidly process and synthesise domain-specific scientific knowledge. In this study, we present a multi-agent Artificial Intelligence (AI) framework designed to support sustainable protein production research, with an initial focus on microbial protein fermentation using side-streams which enables waste carbon capture and utilisation (CCU). Our Retrieval-Augmented Generation (RAG)-oriented system consists of two GPT-based LLM agents: (1) a literature search agent that retrieves relevant scientific literature on microbial protein production for a specified microbial strain, and (2) an information extraction agent that processes the retrieved content to extract relevant biological and chemical information. Two parallel methodologies, fine-tuning and prompt engineering, were explored for agent optimisation. Both methods demonstrated effectiveness at improving the performance of the information extraction agent in terms of transformer-based cosine similarity scores between obtained and ideal outputs. Mean cosine similarity scores were increased by up to 25 %, while universally reaching mean scores of ≥0.89 against ideal output text. Fine-tuning overall improved the mean scores to a greater extent (consistently of ≥0.94) compared to prompt engineering, although lower statistical uncertainties were observed with the latter approach. A user interface was developed and published for enabling the use of the multi-agent AI system, alongside preliminary exploration of additional chemical safety-based search capabilities relevant to CCU-integrated sustainable protein production. © 2025 The Author(s). Published by Elsevier Ltd on behalf of Institution of Chemical Engineers (IChemE). This is an open access article under the CC BY license. http://creativecommons.org/licenses/by/4.0/ | I15: Include | P15: =IF(K15="Eligible",IF(M15=1,1000,0)+IF(N15="Y",100,0)+IF(O15="Y",10,0)+(C15-2019)/10,"") | Q15: =IF(P15="","",RANK(P15,$P$2:$P$45)) | S15: =IF(I15="","Pending",IF(I15="Exclude","Excluded at title/abstract",IF(V15="Y","Excluded: eligible by abstract, not assessed (E9)",IF(K15="","Pending full text",IF(K15="Exclude","Excluded at full text",IF(K15="Not retrieved","Not retrieved",IF(R15="Yes","Included",IF(R15="No","Excluded: eligible, not selected (E9)","Eligible - pending selection")))))))) -> Pending full text
A16: 15 | B16: Nguyen T.-A. | C16: 2026 | D16: Debating to verify: A robust and explainable multi-agent LLM system for fact-checking | E16: ICT Express | F16: 10.1016/j.icte.2026.05.017 | G16: English | H16: Large language models have advanced automated fact verification, yet single-agent prompting remains prone to hallucination, while fine-tuned models suffer from limited scalability and cross-domain generalization. This paper proposes FC-MAD, a training-free multi-agent debate framework that coordinates multiple LLMs through structured critique, context summarization, and judge-guided consensus reasoning. Extensive experiments on Vietnamese (ViFactCheck), multilingual (X-Fact), and English (FEVER) benchmarks show that FC-MAD consistently outperforms strong fine-tuned and prompting-based baselines, achieving state-of-the-art performance on ViFactCheck and FEVER, while delivering robust gains across X-Fact languages. These results highlight the effectiveness of structured multi-agent reasoning for reliable AI-based fact-checking systems. © 2026 The Author(s). | I16: Include | P16: =IF(K16="Eligible",IF(M16=1,1000,0)+IF(N16="Y",100,0)+IF(O16="Y",10,0)+(C16-2019)/10,"") | Q16: =IF(P16="","",RANK(P16,$P$2:$P$45)) | S16: =IF(I16="","Pending",IF(I16="Exclude","Excluded at title/abstract",IF(V16="Y","Excluded: eligible by abstract, not assessed (E9)",IF(K16="","Pending full text",IF(K16="Exclude","Excluded at full text",IF(K16="Not retrieved","Not retrieved",IF(R16="Yes","Included",IF(R16="No","Excluded: eligible, not selected (E9)","Eligible - pending selection")))))))) -> Pending full text
A17: 16 | B17: Lu J. | C17: 2025 | D17: Automated building energy modeling for energy retrofits using a large language model-based multi-agent framework | E17: iScience | F17: 10.1016/j.isci.2025.113867 | G17: English | H17: Building energy modeling is critical for retrofit design, but it is labor-intensive. We present Data2BEM (Data to Building Energy Model), a large language model-based multi-agent framework that parses architectural drawings, specifications, and sensor data to automatically generate and calibrate building energy simulations. Applied to an existing University of Cambridge office building, Data2BEM produced a calibrated model meeting industry accuracy benchmarks and enabled the assessment of heat-electrification retrofits. Relative to professional practice, the system reduced total modeling time by over 90% (48 min versus 8–32 h) with minimal human input. The workflow integrates information extraction, model generation, and data-driven calibration, delivering end-to-end automation while accurately reflecting measured performance. These results indicate that large language model-driven multi-agent methods can accelerate retrofit analysis, lowering expertise and time barriers for practitioners and supporting scalable pathways to building-sector decarbonization. © 2025 The Authors | I17: Exclude | J17: E5 | P17: =IF(K17="Eligible",IF(M17=1,1000,0)+IF(N17="Y",100,0)+IF(O17="Y",10,0)+(C17-2019)/10,"") | Q17: =IF(P17="","",RANK(P17,$P$2:$P$45)) | S17: =IF(I17="","Pending",IF(I17="Exclude","Excluded at title/abstract",IF(V17="Y","Excluded: eligible by abstract, not assessed (E9)",IF(K17="","Pending full text",IF(K17="Exclude","Excluded at full text",IF(K17="Not retrieved","Not retrieved",IF(R17="Yes","Included",IF(R17="No","Excluded: eligible, not selected (E9)","Eligible - pending selection")))))))) -> Excluded at title/abstract
A18: 17 | B18: Vo T. | C18: 2026 | D18: Unsupervised column relevance extraction for table-based fact verification via structured and explainable large language model reasoning | E18: Computers and Electrical Engineering | F18: 10.1016/j.compeleceng.2026.111473 | G18: English | H18: Recent advances in large language models have driven remarkable progress in automated reasoning over structured tabular data, with applications spanning healthcare, scientific research, and public policy. Despite significant advancements, state-of-the-art methods face some challenges: they often require complex multi-agent or tool-based pipelines, fine-tuning on domain-specific data, or dependence on closed-source commercial models, which can limit accessibility, reproducibility, and transparency. To overcome these limitations, we introduce UCRET, a modular and fully interpretable framework for zero-shot table-based fact verification. UCRET combines open-source large language models with explicit, step-by-step explanations for each possible verification outcome, avoiding both task-specific fine-tuning and reliance on proprietary models. Its key novelty lies in applying spherical k -means to unsupervised, claim-driven column selection , which identifies the most relevant evidence columns before reasoning and reduces the amount of irrelevant tabular information passed to the reasoning stage. Given this reduced table, the model elicits counterfactual explanations for each veracity label and aggregates them into a final decision. This design both clarifies why a label is predicted and limits token usage by focusing the model on salient columns. Empirical results on medical, scientific, and general-domain Wikipedia benchmarks demonstrate that our framework achieves competitive performance while maintaining transparency throughout. Ablations confirm that both the spherical k-means column selector and the counterfactual explanation stage are necessary to achieve the observed accuracy and transparency. © 2026 Elsevier Ltd. | I18: Exclude | J18: E4 | P18: =IF(K18="Eligible",IF(M18=1,1000,0)+IF(N18="Y",100,0)+IF(O18="Y",10,0)+(C18-2019)/10,"") | Q18: =IF(P18="","",RANK(P18,$P$2:$P$45)) | S18: =IF(I18="","Pending",IF(I18="Exclude","Excluded at title/abstract",IF(V18="Y","Excluded: eligible by abstract, not assessed (E9)",IF(K18="","Pending full text",IF(K18="Exclude","Excluded at full text",IF(K18="Not retrieved","Not retrieved",IF(R18="Yes","Included",IF(R18="No","Excluded: eligible, not selected (E9)","Eligible - pending selection")))))))) -> Excluded at title/abstract
A19: 18 | B19: Nagpal R. | C19: 2026 | D19: Mitigating Hallucinations in Finance-Based Multi-Agent Large Language Model Systems | E19: Electronics (Switzerland) | F19: 10.3390/electronics15194456 | G19: English | H19: Large language models are increasingly used for financial question answering, while they are prone to generating hallucinated content. In this research, we propose a multi-signal framework for hallucination detection and mitigation. Our framework combines six signals (entailment, semantic similarity, claim verification, numeric consistency, token overlap and confidence calibration techniques) to identify hallucination type and severity. We evaluated our framework using multiple language models across three financial QA benchmark datasets (FinQA, FinanceQA, and FinDER). Our proposed framework corrects up to 78.4% of the detected hallucinations (fix rate on the hallucinated subset of FinQA; 47.7% on FinanceQA and 45.7% on FinDER), outperforming a type-agnostic mitigation baseline on all three datasets. This highlights that targeted, type-aware hallucination mitigation can significantly improve answer reliability while remaining computationally effective. © 2026 by the authors. | I19: Exclude | J19: E4 | P19: =IF(K19="Eligible",IF(M19=1,1000,0)+IF(N19="Y",100,0)+IF(O19="Y",10,0)+(C19-2019)/10,"") | Q19: =IF(P19="","",RANK(P19,$P$2:$P$45)) | S19: =IF(I19="","Pending",IF(I19="Exclude","Excluded at title/abstract",IF(V19="Y","Excluded: eligible by abstract, not assessed (E9)",IF(K19="","Pending full text",IF(K19="Exclude","Excluded at full text",IF(K19="Not retrieved","Not retrieved",IF(R19="Yes","Included",IF(R19="No","Excluded: eligible, not selected (E9)","Eligible - pending selection")))))))) -> Excluded at title/abstract | T19: Y
A20: 19 | B20: Quelle D. | C20: 2024 | D20: The perils and promises of fact-checking with large language models | E20: Frontiers in Artificial Intelligence | F20: 10.3389/frai.2024.1341697 | G20: English | H20: Automated fact-checking, using machine learning to verify claims, has grown vital as misinformation spreads beyond human fact-checking capacity. Large language models (LLMs) like GPT-4 are increasingly trusted to write academic papers, lawsuits, and news articles and to verify information, emphasizing their role in discerning truth from falsehood and the importance of being able to verify their outputs. Understanding the capacities and limitations of LLMs in fact-checking tasks is therefore essential for ensuring the health of our information ecosystem. Here, we evaluate the use of LLM agents in fact-checking by having them phrase queries, retrieve contextual data, and make decisions. Importantly, in our framework, agents explain their reasoning and cite the relevant sources from the retrieved context. Our results show the enhanced prowess of LLMs when equipped with contextual information. GPT-4 outperforms GPT-3, but accuracy varies based on query language and claim veracity. While LLMs show promise in fact-checking, caution is essential due to inconsistent accuracy. Our investigation calls for further research, fostering a deeper comprehension of when agents succeed and when they fail. Copyright © 2024 Quelle and Bovet. | I20: Maybe | P20: =IF(K20="Eligible",IF(M20=1,1000,0)+IF(N20="Y",100,0)+IF(O20="Y",10,0)+(C20-2019)/10,"") | Q20: =IF(P20="","",RANK(P20,$P$2:$P$45)) | S20: =IF(I20="","Pending",IF(I20="Exclude","Excluded at title/abstract",IF(V20="Y","Excluded: eligible by abstract, not assessed (E9)",IF(K20="","Pending full text",IF(K20="Exclude","Excluded at full text",IF(K20="Not retrieved","Not retrieved",IF(R20="Yes","Included",IF(R20="No","Excluded: eligible, not selected (E9)","Eligible - pending selection")))))))) -> Pending full text
A21: 20 | B21: Alrayzah A. | C21: 2025 | D21: CoAgt: unleashing the reasoning capabilities of large language models on tabular data with a chain of agents | E21: PeerJ Computer Science | F21: 10.7717/peerj-cs.3423 | G21: English | H21: Large language models (LLMs) have shown remarkable progress in text-based reasoning, but they continue to struggle with large and complex tables. Token limitations and the loss of structural dependencies make it difficult for a single model to extract evidence, connect relationships, and produce reliable answers. To address this challenge, we introduce Chain of Agents (CoAgt) a multi-agent framework inspired by how human reason with tables, scanning data, comparing values, retaining information, and making decisions. In CoAgt, different agents share the workload: Collectors gather evidence from subtables, the Synthesizer integrates their findings into a coherent answer, and the Refiner ensures clarity and correctness. This division of labor makes the reasoning process both scalable and interpretable, while reducing the risk of errors that often occur when one model handles all steps alone. We evaluate CoAgt on two widely used benchmarks. On WikiTableQuestions (WikiTQ) it achieves 85.4% accuracy, outperforming the strong Chain-of-Table baseline by more than twenty-five percentage points. On Table Fact-Checking (TabFact) it reaches 96.6% accuracy, exceeding previous state-of-the-art results. These findings show that breaking reasoning into specialized agents not only improves performance but also offers a transparent and reliable approach for reasoning over large, complex tables. Copyright 2025 Alrayzah and Alqhtani. Distributed under Creative Commons CC-BY 4.0. http://www.creativecommons.org/licenses/by/4.0/ | I21: Exclude | J21: E6 | P21: =IF(K21="Eligible",IF(M21=1,1000,0)+IF(N21="Y",100,0)+IF(O21="Y",10,0)+(C21-2019)/10,"") | Q21: =IF(P21="","",RANK(P21,$P$2:$P$45)) | S21: =IF(I21="","Pending",IF(I21="Exclude","Excluded at title/abstract",IF(V21="Y","Excluded: eligible by abstract, not assessed (E9)",IF(K21="","Pending full text",IF(K21="Exclude","Excluded at full text",IF(K21="Not retrieved","Not retrieved",IF(R21="Yes","Included",IF(R21="No","Excluded: eligible, not selected (E9)","Eligible - pending selection")))))))) -> Excluded at title/abstract | T21: Y
A22: 21 | B22: Ghosh S. | C22: 2026 | D22: LLM-based AI agents for automated extraction of material properties and structural features | E22: Computational Materials Science | F22: 10.1016/j.commatsci.2026.114521 | G22: English | H22: The lack of large, machine-readable datasets continues to constrain data-driven materials discovery. We present a closed-loop, agentic large-language-model (LLM) workflow that autonomously extracts thermoelectric and structural properties from ∼ 10,000 full-text scientific articles. The framework integrates context-engineered multi-agent orchestration , dynamic token allocation , and a built-in LLM-Judge that performs schema-level consistency checks to suppress hallucinated or malformed outputs. Unlike prior systems restricted to narrative text, our workflow unifies text, tables, and captions under a single reasoning graph, enabling cross-modal extraction and automated validation of tabular data. Benchmarking on a manually curated set of 50 papers shows that GPT-4.1 achieves the highest extraction accuracy (F1≈0.91 for thermoelectric properties, F1≈0.838 for structural fields). At the same time, GPT-4.1 Mini offers nearly comparable performance (F1≈0.889 for thermoelectric, F1≈0.833 for structural) at a fraction of the cost, enabling large-scale deployment. Applying this workflow, we create a data set of 18,869 property temperature records with normalized units, spanning the figure of merit (ZT), Seebeck coefficient, electrical conductivity, power factor, and thermal conductivity, together with structural attributes such as crystal class, space group, and doping strategy. Following chemical validation, 11,927 entries are released through an interactive web explorer supporting semantic filters, numeric queries, and CSV export. Beyond thermoelectrics, this cross-modal, extensible agent architecture establishes a general paradigm for large-scale, verifiable data extraction from unstructured scientific literature. © 2026 Elsevier B.V. | I22: Include | P22: =IF(K22="Eligible",IF(M22=1,1000,0)+IF(N22="Y",100,0)+IF(O22="Y",10,0)+(C22-2019)/10,"") | Q22: =IF(P22="","",RANK(P22,$P$2:$P$45)) | S22: =IF(I22="","Pending",IF(I22="Exclude","Excluded at title/abstract",IF(V22="Y","Excluded: eligible by abstract, not assessed (E9)",IF(K22="","Pending full text",IF(K22="Exclude","Excluded at full text",IF(K22="Not retrieved","Not retrieved",IF(R22="Yes","Included",IF(R22="No","Excluded: eligible, not selected (E9)","Eligible - pending selection")))))))) -> Pending full text
A23: 22 | B23: Zhang L. | C23: 2025 | D23: Automatic building energy model development and debugging using large language models agentic workflow | E23: Energy and Buildings | F23: 10.1016/j.enbuild.2024.115116 | G23: English | H23: Building energy modeling (BEM) is a complex process that demands significant time and expertise, limiting its broader application in building design and operations. While Large Language Models (LLMs) agentic workflow have facilitated complex engineering processes, their application in BEM has not been specifically explored. This paper investigates the feasibility of automating BEM using LLM agentic workflow. We developed a generic LLM-planning-based workflow that takes a building description as input and generates an error-free EnergyPlus building energy model. Our robust workflow includes four core agents: 1) Building Description Pre-Processing, 2) IDF Object Information Extraction, 3) Single IDF Object Generator Suite, and 4) IDF Debugging Agent. These agents divide the complex tasks into manageable sub-steps, enabling LLMs to generate accurate and reliable results at each stage. The case study demonstrates the successful translation of a building description into an error-free EnergyPlus model for the iUnit modular building at the National Renewable Energy Laboratory. The effectiveness of our workflow surpasses: 1) naive prompt engineering, 2) other LLM-based workflows, and 3) manual modeling, in terms of accuracy, reliability, and time efficiency. The paper concludes with a discussion on the interplay between foundational models and LLM agent planning design, advocating for the use of fine-tuned, specialized models to advance this field. © 2024 Elsevier B.V. | I23: Exclude | J23: E5 | P23: =IF(K23="Eligible",IF(M23=1,1000,0)+IF(N23="Y",100,0)+IF(O23="Y",10,0)+(C23-2019)/10,"") | Q23: =IF(P23="","",RANK(P23,$P$2:$P$45)) | S23: =IF(I23="","Pending",IF(I23="Exclude","Excluded at title/abstract",IF(V23="Y","Excluded: eligible by abstract, not assessed (E9)",IF(K23="","Pending full text",IF(K23="Exclude","Excluded at full text",IF(K23="Not retrieved","Not retrieved",IF(R23="Yes","Included",IF(R23="No","Excluded: eligible, not selected (E9)","Eligible - pending selection")))))))) -> Excluded at title/abstract
A24: 23 | B24: Odobesku R. | C24: 2025 | D24: Agent-based multimodal information extraction for nanomaterials | E24: npj Computational Materials | F24: 10.1038/s41524-025-01674-7 | G24: English | H24: Automating structured data extraction from scientific literature is a critical challenge with broad implications across domains. We introduce nanoMINER, a multi-agent system combining large language models and multimodal analysis to extract essential information from scientific research articles on nanomaterials. This system processes documents end-to-end, utilizing tools such as YOLO for visual data extraction and GPT-4o for linking textual and visual information. At its core, the ReAct agent orchestrates specialized agents to ensure comprehensive data extraction. We demonstrate the efficacy of the system by automating the assembly of nanomaterial and nanozyme datasets previously manually curated by domain experts. NanoMINER achieves high precision in extracting nanomaterial properties like chemical formulas, crystal systems, and surface characteristics. For nanozymes, we obtain near-perfect precision (0.98) for kinetic parameters and essential features such as Cmin and Cmax. To benchmark the system performance, we also compare nanoMINER to several baseline LLMs, including the most recent multimodal GPT-4.1, and show consistently higher extraction precision and recall. Our approach is extensible to other domains of materials science and fields like biomedicine, advancing data-driven research methodologies and automated knowledge extraction. © The Author(s) 2025. | I24: Include | P24: =IF(K24="Eligible",IF(M24=1,1000,0)+IF(N24="Y",100,0)+IF(O24="Y",10,0)+(C24-2019)/10,"") | Q24: =IF(P24="","",RANK(P24,$P$2:$P$45)) | S24: =IF(I24="","Pending",IF(I24="Exclude","Excluded at title/abstract",IF(V24="Y","Excluded: eligible by abstract, not assessed (E9)",IF(K24="","Pending full text",IF(K24="Exclude","Excluded at full text",IF(K24="Not retrieved","Not retrieved",IF(R24="Yes","Included",IF(R24="No","Excluded: eligible, not selected (E9)","Eligible - pending selection")))))))) -> Pending full text
A25: 24 | B25: Wang X. | C25: 2026 | D25: Multi-source assembly knowledge fusion and assembly agent for robotic assembly; [基于多源装配知识融合与装配智能体的机器人装配方法] | E25: Jisuanji Jicheng Zhizao Xitong/Computer Integrated Manufacturing Systems, CIMS | F25: 10.13196/j.cims.2026.0015 | G25: English | H25: To address the challenges faced by general-purpose Large Language Model (LLM) in assembly task planning and robot control code generation, including insufficient coverage of assembly-domain knowledge, inadequate semantic understanding of specific assemblies, and the lack of real-time feedback and dynamic adjustment capability, a Multi-source Assembly knowledge Fusion and Assembly Agent for Robotic assembly (MAFAR) was proposed. A multi-source assembly dataset was constructed, consisting of digital assemblies, assembly process documents, and assembly skill library. The Graph RAG method was used to achieve semantic fusion and index construction of multi-source assembly knowledge, thereby organizing the knowledge into an assembly knowledge graph to provide assembly information for the LLM. For robotic assembly execution, a closed-loop assembly-agent framework of "Think-Act-Reflect" was designed. The LLM served as the decision core, performing assembly intent parsing in the Think stage. In the Act stage, a hierarchical prompting pipeline of "basic information extraction-task planning-code generation" was established to improve the controllability of LLM generation. In the Reflect stage, a two-stage verification mechanism of "LLM self-reflection plus expert evaluation" was introduced to enable dynamic error correction and retrospective optimization of assembly tasks. Experiments showed that the proposed method could significantly improve the success rate of LLM-driven robotic assembly, enhance the semantic understanding ability of LLM in personalized robotic assembly tasks, and improve the execution stability of robotic assembly tasks. © 2026, CIMS. All rights reserved. | I25: Exclude | J25: E5 | P25: =IF(K25="Eligible",IF(M25=1,1000,0)+IF(N25="Y",100,0)+IF(O25="Y",10,0)+(C25-2019)/10,"") | Q25: =IF(P25="","",RANK(P25,$P$2:$P$45)) | S25: =IF(I25="","Pending",IF(I25="Exclude","Excluded at title/abstract",IF(V25="Y","Excluded: eligible by abstract, not assessed (E9)",IF(K25="","Pending full text",IF(K25="Exclude","Excluded at full text",IF(K25="Not retrieved","Not retrieved",IF(R25="Yes","Included",IF(R25="No","Excluded: eligible, not selected (E9)","Eligible - pending selection")))))))) -> Excluded at title/abstract
A26: 25 | B26: Stănescu D. | C26: 2026 | D26: ARE TWO MINDS BETTER THAN ONE? EVALUATING COLLABORATIVE REASONING IN LLMS | E26: UPB Scientific Bulletin, Series C: Electrical Engineering and Computer Science | G26: English | H26: Large language models (LLMs) have shown strong capabilities in reasoning and problem solving, but their outputs often suffer from inconsistency, shallow verification, and occasional errors. Recent research has suggested that collaboration between multiple LLMs, inspired by human group problem solving, could mitigate these weaknesses. This paper investigates whether collaborative interactions between large language models (LLMs) can outperform solo reasoning. We compared single-agent reasoning against two-agent collaborations using two modes: debate and consensus. Using a quota-aware evaluation threshold, we tested GPT-4.1 and GPT-4o on 30 tasks across two categories: (1) problem solving (mathematical, logical, and role-based reasoning), and (2) fact-checking and factual synthesis. Our results suggest that collaboration improves robustness in tasks requiring multistep reasoning and factual cross-validation, but it introduces additional latency and token usage. We discuss trade-offs between accuracy, efficiency, and cost, providing evidence-based guidance on when “two minds are better than one” in LLM reasoning. © 2026, Politechnica University of Bucharest. All rights reserved. | I26: Exclude | J26: E1 | P26: =IF(K26="Eligible",IF(M26=1,1000,0)+IF(N26="Y",100,0)+IF(O26="Y",10,0)+(C26-2019)/10,"") | Q26: =IF(P26="","",RANK(P26,$P$2:$P$45)) | S26: =IF(I26="","Pending",IF(I26="Exclude","Excluded at title/abstract",IF(V26="Y","Excluded: eligible by abstract, not assessed (E9)",IF(K26="","Pending full text",IF(K26="Exclude","Excluded at full text",IF(K26="Not retrieved","Not retrieved",IF(R26="Yes","Included",IF(R26="No","Excluded: eligible, not selected (E9)","Eligible - pending selection")))))))) -> Excluded at title/abstract
A27: 26 | B27: Zhao X. | C27: 2026 | D27: Debapt: Ontology-driven multi-agent debate for APT adversary profile construction from cyber threat intelligence | E27: Computers and Security | F27: 10.1016/j.cose.2026.104988 | G27: English | H27: Cyber threat intelligence (CTI) reports contain rich information about advanced persistent threat (APT) groups. This information is useful for adversary profile construction. However, turning long and fragmented CTI reports into structured adversary profiles remains difficult. Existing methods mainly rely on named entity and relation extraction pipelines or single large language models (LLMs). These methods often lack explicit semantic constraints for profile-oriented tasks. They are also prone to omission and hallucination when processing long reports. In this paper, we study APT adversary profile construction from CTI reports. We formulate this task as an ontology-constrained profile information extraction task. To support this task, we develop VICTOR, a domain-specific ontology that organizes profile-relevant information into six dimensions. We then propose Debapt, an ontology-driven multi-agent debate framework. Guided by VICTOR, Debapt performs APT adversary profile construction through two debate loops in the entity extraction phase and relation extraction phase. In each loop, role-specialized agents iteratively extract, review, and adjudicate candidate profile-relevant facts under moderator supervision. These extracted results can be further aggregated across reports to support actor-centric adversary profile construction. To evaluate Debapt, we re-annotate three public CTI datasets under a unified profiling schema. Experimental results show that Debapt improves profile-oriented entity and relation extraction over competitive baselines. It extracts more complete and better grounded profile-relevant facts from CTI reports. Case studies further show that these extracted results can support the construction of analytically useful adversary profiles. © 2026 The Authors | I27: Include | P27: =IF(K27="Eligible",IF(M27=1,1000,0)+IF(N27="Y",100,0)+IF(O27="Y",10,0)+(C27-2019)/10,"") | Q27: =IF(P27="","",RANK(P27,$P$2:$P$45)) | S27: =IF(I27="","Pending",IF(I27="Exclude","Excluded at title/abstract",IF(V27="Y","Excluded: eligible by abstract, not assessed (E9)",IF(K27="","Pending full text",IF(K27="Exclude","Excluded at full text",IF(K27="Not retrieved","Not retrieved",IF(R27="Yes","Included",IF(R27="No","Excluded: eligible, not selected (E9)","Eligible - pending selection")))))))) -> Pending full text
A28: 27 | B28: Fagbenro M. | C28: 2026 | D28: Improved multi-agent knowledge sharing system using knowledge graphs for news bias detection and fact-checking | E28: Neural Computing and Applications | F28: 10.1007/s00521-026-11944-0 | G28: English | H28: This research study explores how integrating a multi-agent system with a knowledge graph as shared memory enhances news bias analyses, detection, and fact-checking. Automated fact-checking and verification systems have evolved significantly but often struggle with complex contextual information and advanced narratives. This research examines the potential advantages of structured knowledge graphs, which offer significant advantages over both direct LLM prompting and unstructured RAG retrieval approaches in multi-agent systems for news evaluation. This system was designed and implemented as a framework showing multiple specialized agents using Large Language Models (LLMs) to collaborate while building and referencing a dynamic shared knowledge graph. Experiments conducted on diverse political news article datasets comparing three approaches-RAG baseline, LLM-only, and KG-augmented system-with statistical significance testing showing that integrating knowledge graphs improved performance over both RAG baseline and LLM-only. The result indicates that the multi-agent system with a knowledge graph outperforms baselines (p < 0.01), achieving an F1 of 0.901 for bias detection (vs. 0.287 RAG, 0.713 LLM-only) and an F1 of 0.794 for fact-checking (vs. 0.661 RAG, 0.720 LLM-only). These results show that adding a structured knowledge graph representation to a multi-agent system is much better than unstructured retrieval, with statistically significant improvements in both the RAG baseline and LLM-only. © The Author(s), under exclusive licence to Springer-Verlag London Ltd., part of Springer Nature 2026. | I28: Include | P28: =IF(K28="Eligible",IF(M28=1,1000,0)+IF(N28="Y",100,0)+IF(O28="Y",10,0)+(C28-2019)/10,"") | Q28: =IF(P28="","",RANK(P28,$P$2:$P$45)) | S28: =IF(I28="","Pending",IF(I28="Exclude","Excluded at title/abstract",IF(V28="Y","Excluded: eligible by abstract, not assessed (E9)",IF(K28="","Pending full text",IF(K28="Exclude","Excluded at full text",IF(K28="Not retrieved","Not retrieved",IF(R28="Yes","Included",IF(R28="No","Excluded: eligible, not selected (E9)","Eligible - pending selection")))))))) -> Pending full text
A29: 28 | B29: Yang L. | C29: 2025 | D29: Research on risk decision-making generation method for water conservancy project based on multimodal knowledge graph and large language model | E29: PLOS ONE | F29: 10.1371/journal.pone.0330258 | G29: English | H29: Traditional knowledge graphs of water conservancy project risks have supported risk decision-making. However, they are constrained by limited data modalities and low accuracy in information extraction. A multimodal water conservancy project risk knowledge graph is proposed in this study, along with a synergistic strategy involving multimodal large language models Risk decision-making generation is facilitated through a multi-agent agentic retrieval-augmented generation framework. To enhance visual recognition, a DenseNet-based image classification model is improved by incorporating single-head self-attention and coordinate attention mechanisms. For textual data, risk entities such as locations, components, and events are extracted using a BERT-BiLSTM-CRF architecture. These extracted entities serve as the foundation for constructing the multimodal knowledge graph. To support generation, a multi-agent agentic retrieval-augmented generation mechanism is introduced. This mechanism enhances the reliability and interpretability of risk decision-making outputs. In experiments, the enhanced DenseNet model outperforms the original baseline in both precision and recall for image recognition tasks. In risk decision-making tasks, the proposed approach—combining a multimodal knowledge graph with a multi-agent agentic retrieval-augmented generation method—achieves strong performance on BERTScore and ROUGE-L metrics. This work presents a novel perspective for leveraging multimodal knowledge graphs in water conservancy project risk management. © 2025 Yang et al. This is an open access article distributed under the terms of the Creative Commons Attribution License, which permits unrestricted use, distribution, and reproduction in any medium, provided the original author and source are credited. | I29: Exclude | J29: E5 | P29: =IF(K29="Eligible",IF(M29=1,1000,0)+IF(N29="Y",100,0)+IF(O29="Y",10,0)+(C29-2019)/10,"") | Q29: =IF(P29="","",RANK(P29,$P$2:$P$45)) | S29: =IF(I29="","Pending",IF(I29="Exclude","Excluded at title/abstract",IF(V29="Y","Excluded: eligible by abstract, not assessed (E9)",IF(K29="","Pending full text",IF(K29="Exclude","Excluded at full text",IF(K29="Not retrieved","Not retrieved",IF(R29="Yes","Included",IF(R29="No","Excluded: eligible, not selected (E9)","Eligible - pending selection")))))))) -> Excluded at title/abstract
A30: 29 | B30: Tong X. | C30: 2025 | D30: T2F: a domain-agnostic multi-agent framework for unstructured text to factuality evaluation items generation | E30: Discover Artificial Intelligence | F30: 10.1007/s44163-025-00294-w | G30: English | H30: Large language models (LLMs) demonstrate exceptional linguistic capabilities in text generation but remain prone to factual errors, particularly in specialized domains. Traditional factuality evaluation methods primarily rely on human annotation, which is costly, time-consuming, and difficult to generalize across different domains. To address these limitations, this study proposes an innovative multi-agent framework-T2F (Text-to-Factuality)-designed to automatically convert unstructured text into high-quality factuality evaluation datasets. T2F operates through the coordinated efforts of four specialized agents: Analysis, Information Extraction, Generation, and Validation. By systematically processing input data, T2F autonomously generates multiple types of assessment items-including single-choice questions, fill-in-the-blank questions, and true/false statements-without requiring human annotation, while maintaining strong cross-domain applicability. Experimental results demonstrate that T2F achieves data conversion success rates of 99% in the World Heritage domain, 98% in the Medical domain, and 85% in the Film domain. The generated data effectively assess LLMs’ factuality accuracy, highlighting T2F’s capability as a scalable and domain-agnostic factuality evaluation framework. © The Author(s) 2025. | I30: Include | P30: =IF(K30="Eligible",IF(M30=1,1000,0)+IF(N30="Y",100,0)+IF(O30="Y",10,0)+(C30-2019)/10,"") | Q30: =IF(P30="","",RANK(P30,$P$2:$P$45)) | S30: =IF(I30="","Pending",IF(I30="Exclude","Excluded at title/abstract",IF(V30="Y","Excluded: eligible by abstract, not assessed (E9)",IF(K30="","Pending full text",IF(K30="Exclude","Excluded at full text",IF(K30="Not retrieved","Not retrieved",IF(R30="Yes","Included",IF(R30="No","Excluded: eligible, not selected (E9)","Eligible - pending selection")))))))) -> Pending full text
A31: 30 | B31: Paetzold F. | C31: 2026 | D31: From weak signals to risk indicators: An LLM-based information extraction architecture for IT project risk management | E31: Electronic Markets | F31: 10.1007/s12525-026-00928-6 | G31: English | H31: Effective risk management is crucial yet challenging in modern projects because early warning signals often surface in informal, unstructured data sources and evolve as project contexts change. Since prevailing project risk management (PRM) practices largely depend on structured inputs and episodic control routines, they can miss these subtle signals, creating a temporal detection gap between risk emergence and formal identification. This paper introduces an LLM-based architecture for information extraction in PRM. Following a Design Science Research approach, we design, instantiate, and evaluate it, governed by two complementary flows: an Information Flow that continuously transforms heterogeneous project communication into structured, evidence-linked risk indicators through domain-specialized extraction and cross-source reconciliation, and an Extraction Control Flow that versions extraction behavior to remain adaptable, transparent, and auditable. We abstract four nascent design principles capturing transferable design knowledge for LLM-based information extraction in dynamic, context-rich domains. © The Author(s) 2026. | I31: Include | P31: =IF(K31="Eligible",IF(M31=1,1000,0)+IF(N31="Y",100,0)+IF(O31="Y",10,0)+(C31-2019)/10,"") | Q31: =IF(P31="","",RANK(P31,$P$2:$P$45)) | S31: =IF(I31="","Pending",IF(I31="Exclude","Excluded at title/abstract",IF(V31="Y","Excluded: eligible by abstract, not assessed (E9)",IF(K31="","Pending full text",IF(K31="Exclude","Excluded at full text",IF(K31="Not retrieved","Not retrieved",IF(R31="Yes","Included",IF(R31="No","Excluded: eligible, not selected (E9)","Eligible - pending selection")))))))) -> Pending full text
A32: 31 | B32: Zou X. | C32: 2025 | D32: MRBalance: A framework for enhancing event causality identification in multi-agent debates via role assignment | E32: Knowledge-Based Systems | F32: 10.1016/j.knosys.2025.114470 | G32: English | H32: The rapid development of large language models (LLMs) has advanced natural language processing by improving contextual understanding and generalization abilities. However, despite these advances, determining event causality remains a challenging task. When LLMs are applied to this task, they frequently exhibit significant inconsistencies in recognizing causal representations, resulting in the phenomenon known as causal hallucinations. Specifically, LLMs perform well in predicting events with causal relationships but struggle with events without such relationships, frequently failing to achieve balanced performance across different causal scenarios. In this study, we propose MRBalance, a novel framework that uses role-based multi-agent debates to improve event causality identification. Our method transforms the task into a single-choice question-answering task, prompting LLM-based agents to engage in structured debates and justify their answers using their unique role-based perspectives. In addition, we introduce a mechanism for optimizing team members that selects the best agents to participate in the next debate when the debate rounds are lengthy. Extensive experiments on two benchmark datasets demonstrate significant performance improvements, highlighting the effectiveness of MRBalance in reducing causal hallucinations and increasing robustness. © 2025 Elsevier B.V. | I32: Include | P32: =IF(K32="Eligible",IF(M32=1,1000,0)+IF(N32="Y",100,0)+IF(O32="Y",10,0)+(C32-2019)/10,"") | Q32: =IF(P32="","",RANK(P32,$P$2:$P$45)) | S32: =IF(I32="","Pending",IF(I32="Exclude","Excluded at title/abstract",IF(V32="Y","Excluded: eligible by abstract, not assessed (E9)",IF(K32="","Pending full text",IF(K32="Exclude","Excluded at full text",IF(K32="Not retrieved","Not retrieved",IF(R32="Yes","Included",IF(R32="No","Excluded: eligible, not selected (E9)","Eligible - pending selection")))))))) -> Pending full text
A33: 32 | B33: Jeong S. | C33: 2026 | D33: Tool-MAD: A Multi-Agent Debate Framework for Fact Verification with Diverse Tool Augmentation and Adaptive Retrieval | E33: IEEE Access | F33: 10.1109/ACCESS.2026.3716053 | G33: English | H33: Large Language Models (LLMs) often suffer from hallucinations and factual inaccuracies, particularly in complex reasoning and fact verification tasks. Multi-Agent Debate (MAD) systems aim to improve answer accuracy by enabling multiple LLM agents to engage in dialogue, promoting diverse reasoning and mutual verification. However, existing MAD frameworks primarily rely on internal knowledge or static documents, making them vulnerable to hallucinations. While multi-agent debate with knowledge-enhanced framework (MADKE) introduces external evidence to mitigate this issue, its one-time retrieval mechanism limits adaptability to new arguments or emerging information during the debate. To address these limitations, we propose Tool-MAD, a multi-agent debate framework that enhances factual verification by assigning each agent a distinct external tool, such as a search API or a RAG module. Tool-MAD introduces three key innovations: (1) a multi-agent debate framework in which agents leverage heterogeneous external tools to encourage diverse perspectives, (2) an adaptive query formulation mechanism that iteratively refines evidence retrieval as the debate progresses, and (3) the integration of Faithfulness and Answer Relevance scores into the final decision process, enabling the Judge agent to quantitatively evaluate response grounding and question alignment. Experimental results on four fact verification benchmarks show that Tool-MAD consistently outperforms MAD and achieves stronger or comparable performance than MADKE, with performance improvements of up to 11.2 percentage points over MAD and 8.0 percentage points over MADKE. Furthermore, experiments in medically specialized domains demonstrate that Tool-MAD maintains stable performance across different tool configurations and domain conditions, suggesting strong potential for broader real-world fact-checking applications. © 2013 IEEE. | I33: Include | P33: =IF(K33="Eligible",IF(M33=1,1000,0)+IF(N33="Y",100,0)+IF(O33="Y",10,0)+(C33-2019)/10,"") | Q33: =IF(P33="","",RANK(P33,$P$2:$P$45)) | S33: =IF(I33="","Pending",IF(I33="Exclude","Excluded at title/abstract",IF(V33="Y","Excluded: eligible by abstract, not assessed (E9)",IF(K33="","Pending full text",IF(K33="Exclude","Excluded at full text",IF(K33="Not retrieved","Not retrieved",IF(R33="Yes","Included",IF(R33="No","Excluded: eligible, not selected (E9)","Eligible - pending selection")))))))) -> Pending full text
A34: 33 | B34: SHI D. | C34: 2026 | D34: RCRQ: Multi-agent Information Extraction Framework for Traffic Accident Texts; [RCRQ:面向交通事故文本的多智能体信息抽取框架] | E34: Journal of Frontiers of Computer Science and Technology | F34: 10.3778/j.issn.1673-9418.2508069 | G34: English | H34: Building on the police traffic authority’s reliance on textual evidence for handling and regulating autonomous-vehicle (AV) incidents, this paper addresses extraction challenges posed by heterogeneous report genres, frequent cross-sentence coreference, disordered timelines, and missing causal statements. This paper proposes a multi-agent entity-event-relation structured information-extraction framework that treats large language models (LLMs) as agents and produces interpretable, high-confidence outputs through multi-stage processing, to support knowledge-graph construction and rule mining. For the constructed Accident-Benchmark dataset, this paper generates gold annotations via a dual-model collaboration with human-in-the-loop (HITL) verification. Then, this paper uses progressive prompt screening to select the best performer as the single- agent baseline. This paper designs an RCRQ MA framework that enhances extraction through staged reasoning, targeted error diagnosis, iterative repair, and consistency checking, and introduces a joint distillation method that leverages both reasoning trajectories and final outputs to further reduce inference cost. Experiments show that, relative to the single-agent baseline, the RCRQ MA framework yields substantial gains: on DeepSeek-V3, F1 for entities, event triggers, and event arguments improves by 1.89, 7.32, and 5.75 percentage points, respectively; on GLM-4-9B, the human-evaluation average score for relation extraction increases by 0.4 on a five-point scale. Both models outperform alternative baselines, validating the effectiveness of the proposed approach. | I34: Include | P34: =IF(K34="Eligible",IF(M34=1,1000,0)+IF(N34="Y",100,0)+IF(O34="Y",10,0)+(C34-2019)/10,"") | Q34: =IF(P34="","",RANK(P34,$P$2:$P$45)) | S34: =IF(I34="","Pending",IF(I34="Exclude","Excluded at title/abstract",IF(V34="Y","Excluded: eligible by abstract, not assessed (E9)",IF(K34="","Pending full text",IF(K34="Exclude","Excluded at full text",IF(K34="Not retrieved","Not retrieved",IF(R34="Yes","Included",IF(R34="No","Excluded: eligible, not selected (E9)","Eligible - pending selection")))))))) -> Pending full text
A35: 34 | B35: Chang L.-J. | C35: 2026 | D35: FactualRAG: a RAG-Powered framework for LLM fact-checking via IFCN-Accredited sources | E35: Journal of Intelligent Information Systems | F35: 10.1007/s10844-026-01041-y | G35: English | H35: The proliferation of misinformation on digital platforms has intensified the demand for accurate and scalable fact-checking. This paper introduces FactualRAG, a retrieval augmented generation (RAG) framework that grounds large language models (LLMs) in external evidence to improve factual accuracy and transparency. FactualRAG combines hybrid retrieval with modular reasoning, aiming to reduce the risk of ungrounded model outputs and support verifiable claim checking. Evaluations across multiple datasets show substantial improvements on AVeriTeC and MultiFC, while results on Climate-Fever highlight the limits of retrieval when coverage is weak. We further test a lightweight Debate extension among multiple LLM agents, which yields incremental gains under strong evidence conditions. Among models, Gemma 2:9b achieves the strongest results on AVeriTeC and MultiFC, though no single model dominates across all benchmarks. Overall, these findings clarify when retrieval-driven methods are most effective and how multi-agent debate can complement them, offering practical guidance for building reliable, interpretable fact-checking tools in journalism, policy, and content moderation. © The Author(s), under exclusive licence to Springer Science+Business Media, LLC, part of Springer Nature 2026. | I35: Include | P35: =IF(K35="Eligible",IF(M35=1,1000,0)+IF(N35="Y",100,0)+IF(O35="Y",10,0)+(C35-2019)/10,"") | Q35: =IF(P35="","",RANK(P35,$P$2:$P$45)) | S35: =IF(I35="","Pending",IF(I35="Exclude","Excluded at title/abstract",IF(V35="Y","Excluded: eligible by abstract, not assessed (E9)",IF(K35="","Pending full text",IF(K35="Exclude","Excluded at full text",IF(K35="Not retrieved","Not retrieved",IF(R35="Yes","Included",IF(R35="No","Excluded: eligible, not selected (E9)","Eligible - pending selection")))))))) -> Pending full text
A36: 35 | B36: Sharifuzzaman Sagar A.S.M. | C36: 2026 | D36: Fact or Fake? Assessing the Role of Deepfake Detectors in Multimodal Misinformation Detection | E36: IEEE Access | F36: 10.1109/ACCESS.2026.3686437 | G36: English | H36: In multimodal misinformation, deception usually arises not just from pixel-level manipulations in an image, but from the semantic and contextual claim jointly expressed by the image–text pair. Yet most deepfake detectors, engineered to detect pixel-level forgeries, do not account for claim-level meaning, despite their growing integration in automated fact-checking (AFC) pipelines. This raises a central scientific and practical question: Do pixel-level detectors contribute useful signal for verifying image–text claims, or do they instead introduce misleading authenticity priors that undermine evidence-based reasoning? We provide the first systematic analysis of deepfake detectors in the context of multimodal misinformation detection. Using two complementary benchmarks such as MMFakeBench and DGM4, we evaluate: i) state-of-the-art image-only deepfake detectors, ii) an evidence-driven fact-checking system that performs tool-guided retrieval via Monte Carlo Tree Search (MCTS) and engages in deliberative inference through Multi-Agent Debate (MAD), and iii) a hybrid fact-checking system that injects detector outputs as auxiliary evidence. Results across both benchmark datasets show that deepfake detectors offer limited standalone value, achieving F1 scores in the range of 0.26–0.53 on MMFakeBench and 0.33–0.49 on DGM4, and that incorporating their predictions into fact-checking pipelines consistently reduces performance by 0.04–0.08 F1 due to non-causal authenticity assumptions. In contrast, the evidence-centric fact-checking system achieves the highest performance, reaching F1 scores of approximately 0.81 on MMFakeBench and 0.55 on DGM4. Overall, our findings demonstrate that multimodal claim verification is driven primarily by semantic understanding and external evidence, and that pixel-level artifact signals do not reliably enhance reasoning over real-world image–text misinformation. © 2026 The Authors. | I36: Include | P36: =IF(K36="Eligible",IF(M36=1,1000,0)+IF(N36="Y",100,0)+IF(O36="Y",10,0)+(C36-2019)/10,"") | Q36: =IF(P36="","",RANK(P36,$P$2:$P$45)) | S36: =IF(I36="","Pending",IF(I36="Exclude","Excluded at title/abstract",IF(V36="Y","Excluded: eligible by abstract, not assessed (E9)",IF(K36="","Pending full text",IF(K36="Exclude","Excluded at full text",IF(K36="Not retrieved","Not retrieved",IF(R36="Yes","Included",IF(R36="No","Excluded: eligible, not selected (E9)","Eligible - pending selection")))))))) -> Pending full text
A37: 36 | B37: Liu Z. | C37: 2025 | D37: A more advanced group polarization measurement approach based on LLM-based agents and graphs | E37: Information Research | F37: 10.47989/ir30iConf47578 | G37: English | H37: Introduction. Group polarization is an important research direction in social media content analysis, attracting many researchers to explore this field. Therefore, how to effectively measure group polarization has become a critical topic. Measuring group polarization on social media presents several challenges that have not yet been addressed by existing solutions. First, social media group polarization measurement involves processing vast amounts of text, which poses a significant challenge for information extraction. Second, social media texts often contain hard-to-understand content, including sarcasm, emojis, and internet slang. Additionally, group polarization research focuses on holistic analysis, while texts is typically fragmented. These challenges indicate that a new solution needs to be proposed. Method. To address these challenges, we designed a solution based on a multi-agent system and used a graph-structured community sentiment network (CSN) to represent polarization states. Furthermore, we developed a metric called community opposition index (COI) based on the CSN to quantify polarization. Conclusion. We tested our multi-agent system through a zero-shot stance detection task and achieved outstanding results, which proved its significant value in terms of usability and accuracy. © The Author(s). | I37: Include | P37: =IF(K37="Eligible",IF(M37=1,1000,0)+IF(N37="Y",100,0)+IF(O37="Y",10,0)+(C37-2019)/10,"") | Q37: =IF(P37="","",RANK(P37,$P$2:$P$45)) | S37: =IF(I37="","Pending",IF(I37="Exclude","Excluded at title/abstract",IF(V37="Y","Excluded: eligible by abstract, not assessed (E9)",IF(K37="","Pending full text",IF(K37="Exclude","Excluded at full text",IF(K37="Not retrieved","Not retrieved",IF(R37="Yes","Included",IF(R37="No","Excluded: eligible, not selected (E9)","Eligible - pending selection")))))))) -> Pending full text
A38: 37 | B38: Iwaszenko S. | C38: 2026 | D38: NLP System for Automation of Document Workflow in a Research and Development Organization—A Case Study | E38: Applied Sciences (Switzerland) | F38: 10.3390/app16094562 | G38: English | H38: Featured Application: The Large language model (LLM)-based system for autonomous document processing was developed with a view to its application in the GIG National Research Institute (GIG-NRI). The system will help with automatic document classification, and depending on the type, information extraction, summarization, or action triggering. The system is in the Minimum Viable Product (MVP) stage, and its further development depends on pilot assessments. Research and development (R&D) organizations face significant operational bottlenecks due to the manual processing of diverse, unstructured documents. This paper presents the design, implementation, and pilot evaluation of an on-premise, multi-agent natural language processing (NLP) system developed for the GIG National Research Institute (GIG-NRI). Built upon a LangGraph architecture, the system utilizes open-weight large language models (LLMs) to perform zero-shot document classification, dynamic routing, and specialized information extraction. We rigorously evaluated the classification agent across twelve different local LLMs under two distinct testing regimes: first, using a strictly defined dataset of known administrative and scientific document types, and second, introducing a subset of out-of-distribution (unclassified) data to test real-world robustness. Our results demonstrate that the 70-billion parameter model (cogito:70b) achieved a peak accuracy of 97.3% in the first regime and maintained a strong 94.3% accuracy when confronted with out-of-spec data. However, our analysis reveals a critical operational trade-off regarding computational efficiency. The 24-billion parameter (magistral:24b) and 32-billion parameter (qwen3:32b) models emerged as the next best in overall accuracy while requiring less than half the processing time of their 70B counterpart. Notably, magistral:24b proved superior for strictly defined document streams, whereas qwen3:32b demonstrated greater robustness when handling out-of-distribution inputs. Furthermore, we demonstrate the efficacy of heterogeneous model assignments for complex multi-stage tasks, such as Scientific Article summarization via hierarchical Map-Reduce. © 2026 by the authors. | I38: Include | K38: Eligible | M38: 1 | N38: N | O38: Y | P38: =IF(K38="Eligible",IF(M38=1,1000,0)+IF(N38="Y",100,0)+IF(O38="Y",10,0)+(C38-2019)/10,"") -> 1010.7 | Q38: =IF(P38="","",1+COUNTIF($P$2:$P$45,">"&P38)) -> 1 | S38: =IF(I38="","Pending",IF(I38="Exclude","Excluded at title/abstract",IF(V38="Y","Excluded: eligible by abstract, not assessed (E9)",IF(K38="","Pending full text",IF(K38="Exclude","Excluded at full text",IF(K38="Not retrieved","Not retrieved",IF(R38="Yes","Included",IF(R38="No","Excluded: eligible, not selected (E9)","Eligible - pending selection")))))))) -> Eligible - pending selection
A39: 38 | B39: Hsu E. | C39: 2025 | D39: LLM-IE: a python package for biomedical generative information extraction with large language models | E39: JAMIA Open | F39: 10.1093/jamiaopen/ooaf012 | G39: English | H39: Objectives: Despite the recent adoption of large language models (LLMs) for biomedical information extraction (IE), challenges in prompt engineering and algorithms persist, with no dedicated software available. To address this, we developed LLM-IE: a Python package for building complete IE pipelines. Materials and Methods: The LLM-IE supports named entity recognition, entity attribute extraction, and relation extraction tasks. We benchmarked it on the i2b2 clinical datasets. Results: The sentence-based prompting algorithm resulted in the best 8-shot performance of over 70% strict F1 for entity extraction and about 60% F1 for entity attribute extraction. Discussion: We developed a Python package, LLM-IE, highlighting (1) an interactive LLM agent to support schema definition and prompt design, (2) state-of-the-art prompting algorithms, and (3) visualization features. Conclusion: The LLM-IE provides essential building blocks for developing robust information extraction pipelines. Future work will aim to expand its features and further optimize computational efficiency. © The Author(s) 2025. Published by Oxford University Press on behalf of the American Medical Informatics Association. | I39: Exclude | J39: E4 | P39: =IF(K39="Eligible",IF(M39=1,1000,0)+IF(N39="Y",100,0)+IF(O39="Y",10,0)+(C39-2019)/10,"") | Q39: =IF(P39="","",RANK(P39,$P$2:$P$45)) | S39: =IF(I39="","Pending",IF(I39="Exclude","Excluded at title/abstract",IF(V39="Y","Excluded: eligible by abstract, not assessed (E9)",IF(K39="","Pending full text",IF(K39="Exclude","Excluded at full text",IF(K39="Not retrieved","Not retrieved",IF(R39="Yes","Included",IF(R39="No","Excluded: eligible, not selected (E9)","Eligible - pending selection")))))))) -> Excluded at title/abstract | T39: Y
A40: 39 | B40: Dong Y. | C40: 2026 | D40: Multi-agent systems and credibility-based advanced scoring mechanism in fact-checking | E40: Scientific Reports | F40: 10.1038/s41598-026-41862-z | G40: English | H40: Fact-checking is crucial as rumours and misinformation negatively impact social networking services (SNS) and online discussions, often leading to the spread of misinformation. Meanwhile, fact-checking with large language models (LLMs) is becoming increasingly popular with the increase in the performance of LLMs. However, the previous works have issues, including overconfidence in the judgment results of LLM and the insufficiency of binary fact-checking due to the text’s complexity. On the other hand, using multiple information sources to make judgments reveals another obstacle: the lack of proper scoring mechanisms. Thus, we propose a framework called multi-agent fact-checking (MAFC), which includes multiple agents with unique information sources to measure the text’s credibility. Specifically, a brand-new scoring mechanism is also used to calculate credibility according to each agent’s judgment results and confidence. We tested our proposed method through several comparative experiments. The results of the experiments prove that the proposed method performs better than other baselines in both the binary fact-checking task and the multi-label fact-checking task. Finally, the challenges and obstacles existing in fact-checking fields, such as the definition standards and dataset creation, are discussed. © The Author(s) 2026. | I40: Include | P40: =IF(K40="Eligible",IF(M40=1,1000,0)+IF(N40="Y",100,0)+IF(O40="Y",10,0)+(C40-2019)/10,"") | Q40: =IF(P40="","",RANK(P40,$P$2:$P$45)) | S40: =IF(I40="","Pending",IF(I40="Exclude","Excluded at title/abstract",IF(V40="Y","Excluded: eligible by abstract, not assessed (E9)",IF(K40="","Pending full text",IF(K40="Exclude","Excluded at full text",IF(K40="Not retrieved","Not retrieved",IF(R40="Yes","Included",IF(R40="No","Excluded: eligible, not selected (E9)","Eligible - pending selection")))))))) -> Pending full text
A41: 40 | B41: Elmitwalli S. | C41: 2025 | D41: Development and validation of a multi-agent AI pipeline for automated credibility assessment of tobacco misinformation: a proof-of-concept study | E41: Frontiers in Artificial Intelligence | F41: 10.3389/frai.2025.1659861 | G41: English | H41: Background: The proliferation of tobacco-related misinformation poses significant public health risks, requiring scalable solutions for credibility assessment. Traditional manual fact-checking approaches are resource-intensive and cannot match the pace of misinformation spread. Objective: To develop and validate a proof-of-concept multi-agent AI pipeline for automated credibility assessment of tobacco misinformation claims, evaluating its performance against expert human reviewers. Methods: We constructed a three-agent pipeline using OpenAI GPT-4.1 and the Crewai framework. The Serper API provided real-time evidence retrieval. The Content Analyzer classifies claims into four types: health impact, scientific assertion, policy, or statistical. The Scientific Fact Verifier queries authoritative sources (WHO, CDC, PubMed Central, Cochrane). The Health Evidence Assessor applies weighted scoring across five dimensions to assign 0–100 credibility scores on a five-level scale. Results: The framework achieved an MAE of 6.25 points against expert scores, a weighted Cohen’s κ of 0.68 (95% CI: 0.52–0.84) indicating substantial agreement, 70% exact category agreement, 95% adjacent-level agreement, and processed each claim in under 7 s—over 1,000 × faster than manual review. Limitations: We validated our approach using 20 diverse tobacco claims through intensive expert review (2–4 h per claim). The system exhibited a conservative bias (+3.25 points, p = 0.03) and did not classify any claims as “Highly Unlikely” despite expert assignment of two claims to this category. This proof-of-concept demonstrates technical feasibility and substantial inter-rater agreement while identifying areas for calibration in future large-scale implementations. Conclusion: Our proof-of-concept agentic AI pipeline demonstrates substantial agreement with expert assessments of tobacco-related claims while providing dramatic speed improvements. By combining zero-shot LLM reasoning, retrieval-grounded evidence verification, and a transparent five-level scoring schema, the system offers a practical tool for real-time misinformation monitoring in public health. This proof-of-concept establishes technical feasibility for automated tobacco misinformation assessment, with validation results supporting further development and larger-scale testing before operational deployment. Copyright © 2025 Elmitwalli, Mehegan, Braznell and Gallagher. | I41: Include | P41: =IF(K41="Eligible",IF(M41=1,1000,0)+IF(N41="Y",100,0)+IF(O41="Y",10,0)+(C41-2019)/10,"") | Q41: =IF(P41="","",RANK(P41,$P$2:$P$45)) | S41: =IF(I41="","Pending",IF(I41="Exclude","Excluded at title/abstract",IF(V41="Y","Excluded: eligible by abstract, not assessed (E9)",IF(K41="","Pending full text",IF(K41="Exclude","Excluded at full text",IF(K41="Not retrieved","Not retrieved",IF(R41="Yes","Included",IF(R41="No","Excluded: eligible, not selected (E9)","Eligible - pending selection")))))))) -> Pending full text
A42: 41 | B42: Situ R. | C42: 2026 | D42: Self-improving multi-agent framework for zero-shot multimodal information extraction | E42: Expert Systems with Applications | F42: 10.1016/j.eswa.2026.132010 | G42: English | H42: Zero-shot multimodal information extraction (MIE) aims to extract structured information from multimedia content without relying on annotated data, posing significant challenges due to minimal human intervention. Recent efforts adapt large language models (LLMs) to this task, leveraging their strong generalization capabilities. While promising, two key limitations remain: (i) most methods rely on single-turn or multi-turn interactions with a single LLM, which struggle with complex schemas, long input contexts, and nuanced instruction following; and (ii) demonstration retrieval is often based on shallow semantic similarity, neglecting entity-level relevance and misleading LLMs during inference. To address these challenges, we propose a self-improving multi-agent system (SIMAS) for zero-shot MIE. SIMAS comprises three specialized LLM-based agents: (i) a task-agnostic demonstration selector that retrieves entity-aware samples from unlabeled corpora, (ii) an machine reading comprehension (MRC)-based self-annotator that formulates annotation as a multiple-choice question answering (QA) task and employs a multi-agent debate (MD) mechanism for improved reliability, and (iii) a retrieval-augmented code generation predictor that reformulates MIE as structured code generation problems, guided by the self-annotated demonstrations. By distributing complex MIE problem across cooperative agents, SIMAS mitigates performance degradation from overloading a single agent and stimulates the self-learning capabilities of LLMs. Experiments on six benchmarks show that SIMAS consistently achieves state-of-the-art zero-shot performance, and remarkably, surpasses fine-tuned models trained on large-scale labeled data in three benchmarks. © 2026 Published by Elsevier Ltd. | I42: Include | P42: =IF(K42="Eligible",IF(M42=1,1000,0)+IF(N42="Y",100,0)+IF(O42="Y",10,0)+(C42-2019)/10,"") | Q42: =IF(P42="","",RANK(P42,$P$2:$P$45)) | S42: =IF(I42="","Pending",IF(I42="Exclude","Excluded at title/abstract",IF(V42="Y","Excluded: eligible by abstract, not assessed (E9)",IF(K42="","Pending full text",IF(K42="Exclude","Excluded at full text",IF(K42="Not retrieved","Not retrieved",IF(R42="Yes","Included",IF(R42="No","Excluded: eligible, not selected (E9)","Eligible - pending selection")))))))) -> Pending full text
A43: 42 | B43: Ma X. | C43: 2026 | D43: Guided and knowledgeable multi-agent debate for fact verification | E43: Expert Systems with Applications | F43: 10.1016/j.eswa.2025.130103 | G43: English | H43: The rapid dissemination of misinformation through social media and open-access platforms has seriously affected public and personal lives and raised data security concerns. Fact verification plays a pivotal role in curbing the spread of such information. While Large Language Models have shown strong capabilities in reasoning and generation, their inherent issues—such as hallucination and bias—can lead to unreliable and logically inconsistent outputs, making them less trustworthy in fact verification tasks. To address these limitations, we propose GKMAD (Guided and Knowledgeable Multi-Agent Debate), a multi-agent fact verification framework designed to enhance reliability by incorporating structured guidance and external knowledge. Specifically, GKMAD incorporates four key mechanisms: (1) a Guided Debate Mechanism that introduces structured prompts to steer agent debates in a targeted and coherent manner; (2) a Knowledgeable Debate Mechanism that enables agents to dynamically incorporate external knowledge to enhance the informativeness and knowledge coverage of the debate; (3) an Advanced Advice Mechanism that generates structured advice from debate outcomes to guide final verification; and (4) a Knowledgeable Verification Mechanism that combines retrieved evidence and debate insights for comprehensive decision-making. Experimental results the FOLK benchmark datasets—constructed from representative subsets of HoVER, FEVEROUS, and SciFact-Open—across seven fact verification tasks demonstrate that GKMAD consistently outperforms state-of-the-art baselines in terms of Macro-F1, confirming the effectiveness of guidance and knowledge integration in mitigating LLM unreliability in fact verification. © 2025 Elsevier Ltd. All rights are reserved, including those for text and data mining, AI training, and similar technologies. | I43: Include | P43: =IF(K43="Eligible",IF(M43=1,1000,0)+IF(N43="Y",100,0)+IF(O43="Y",10,0)+(C43-2019)/10,"") | Q43: =IF(P43="","",RANK(P43,$P$2:$P$45)) | S43: =IF(I43="","Pending",IF(I43="Exclude","Excluded at title/abstract",IF(V43="Y","Excluded: eligible by abstract, not assessed (E9)",IF(K43="","Pending full text",IF(K43="Exclude","Excluded at full text",IF(K43="Not retrieved","Not retrieved",IF(R43="Yes","Included",IF(R43="No","Excluded: eligible, not selected (E9)","Eligible - pending selection")))))))) -> Pending full text | T43: Y
A44: 43 | B44: Song X. | C44: 2026 | D44: Enhancing global value chain transparency: A multi-agent AI framework for detecting ESG greenwashing with open-source innovations | E44: Journal of Business Research | F44: 10.1016/j.jbusres.2026.116242 | G44: English | H44: The escalating importance of Environmental, Social, and Governance (ESG) performance in global value chains has intensified the need for credible sustainability verification. While 83% of Fortune 500 companies now disclose ESG reports, our analysis of 1495 A-share firms reveals alarming greenwashing prevalence - 92% of high-risk enterprises selectively omit material sustainability risks. This study addresses two critical gaps in ESG governance: (i) the lack of robust technical solutions for detecting sophisticated greenwashing tactics across multinational supply networks, and (ii) the absence of comprehensive datasets for systematic analysis. We present Agent-Greenwashing, a multi-agent LLM framework for comparing corporate ESG disclosures with negative news and regulatory records. Through simulated stakeholder dialogs (ESG auditors vs corporate communicators vs investigative journalists), our system achieves 96.67% detection accuracy - a 25.7% improvement over conventional methods. The framework’s innovation lies in its three-phase detection mechanism: semantic deconstruction (TF–IDF/BERTScore analysis), adversarial fact-checking (through multi-round agent debates), and dynamic risk quantification. Supporting this technical advancement, we contribute the first open-source ”Greenwashing-ESG Dataset” spanning 26 industries, containing 5031 reports with expert-validated annotations (κ[jls-end-space/]=0.85). To ensure methodological rigor, the study employs a tri-layered validation protocol combining algorithmic consensus, expert verification, and strict inter-rater reliability checks. Empirical results demonstrate significant negative correlation between ESG scores and greenwashing severity, providing quantifiable metrics for sustainable investment decisions. By open-sourcing models, codebase, and training architectures, the study offers a reproducible approach for AI-assisted ESG verification and provides empirical evidence on its usefulness in greenwashing detection. By enhancing semantic transparency and factual accuracy, this study not only addresses the root causes of greenwashing but also offers a viable technical solution for credible ESG verification, thereby promoting sustainable development and long-term value creation in global value chains. © 2026 Elsevier Inc. All rights are reserved, including those for text and data mining, AI training, and similar technologies. | I44: Include | P44: =IF(K44="Eligible",IF(M44=1,1000,0)+IF(N44="Y",100,0)+IF(O44="Y",10,0)+(C44-2019)/10,"") | Q44: =IF(P44="","",RANK(P44,$P$2:$P$45)) | S44: =IF(I44="","Pending",IF(I44="Exclude","Excluded at title/abstract",IF(V44="Y","Excluded: eligible by abstract, not assessed (E9)",IF(K44="","Pending full text",IF(K44="Exclude","Excluded at full text",IF(K44="Not retrieved","Not retrieved",IF(R44="Yes","Included",IF(R44="No","Excluded: eligible, not selected (E9)","Eligible - pending selection")))))))) -> Pending full text
A45: 44 | B45: Zhu Y. | C45: 2024 | D45: LLMs for knowledge graph construction and reasoning: recent capabilities and future opportunities | E45: World Wide Web | F45: 10.1007/s11280-024-01297-w | G45: English | H45: This paper presents an exhaustive quantitative and qualitative evaluation of Large Language Models (LLMs) for Knowledge Graph (KG) construction and reasoning. We engage in experiments across eight diverse datasets, focusing on four representative tasks encompassing entity and relation extraction, event extraction, link prediction, and question-answering, thereby thoroughly exploring LLMs’ performance in the domain of construction and inference. Empirically, our findings suggest that LLMs, represented by GPT-4, are more suited as inference assistants rather than few-shot information extractors. Specifically, while GPT-4 exhibits good performance in tasks related to KG construction, it excels further in reasoning tasks, surpassing fine-tuned models in certain cases. Moreover, our investigation extends to the potential generalization ability of LLMs for information extraction, leading to the proposition of a Virtual Knowledge Extraction task and the development of the corresponding VINE dataset. Based on these empirical findings, we further propose AutoKG, a multi-agent-based approach employing LLMs and external sources for KG construction and reasoning. We anticipate that this research can provide invaluable insights for future undertakings in the field of knowledge graphs. © The Author(s), under exclusive licence to Springer Science+Business Media, LLC, part of Springer Nature 2024. | I45: Exclude | J45: E4 | P45: =IF(K45="Eligible",IF(M45=1,1000,0)+IF(N45="Y",100,0)+IF(O45="Y",10,0)+(C45-2019)/10,"") | Q45: =IF(P45="","",RANK(P45,$P$2:$P$45)) | S45: =IF(I45="","Pending",IF(I45="Exclude","Excluded at title/abstract",IF(V45="Y","Excluded: eligible by abstract, not assessed (E9)",IF(K45="","Pending full text",IF(K45="Exclude","Excluded at full text",IF(K45="Not retrieved","Not retrieved",IF(R45="Yes","Included",IF(R45="No","Excluded: eligible, not selected (E9)","Eligible - pending selection")))))))) -> Excluded at title/abstract

Sheet AI screening
A1: ID | B1: Title | C1: AI proposed decision | D1: AI reason code | E1: AI tier proposal | F1: Rationale (from title/abstract/keywords)
A2: 1 | B2: Research on solid-state battery information mining based on large language models and chain-of-thought reasoning | C2: Maybe | E2: 2 | F2: Information extraction from scientific papers (batteries). Multi-agent only in prompt refinement; check I4 at full text.
A3: 2 | B3: A Multiagent Multimodal Neural Architecture with Probabilistic Evidence Aggregation for Detecting Fake Messages | C3: Include | E3: 2 | F3: Multi-agent LLM/VLM architecture for credibility (fake message) verification; multimodal - confirm text claims are central (I6).
A4: 3 | B4: Towards Reliable Healthcare LLM Agents: A Case Study for Pilgrims during Hajj | C4: Maybe | E4: 2 | F4: Healthcare chatbot plus a secondary validator agent (fact-check). Likely a single chatbot; check I4/I5 at full text.
A5: 4 | B5: MA-APKG: A multi-agent LLM-based method for construction aviation product assembly process knowledge graph | C5: Include | E5: 2 | F5: Multi-agent LLM triple extraction from assembly process texts.
A6: 5 | B6: An LLM-based Fact-Checking Approach for Multilingual Fake News Detection in Short-Form Video News | C6: Include | E6: 2 | F6: Multi-agent LLM fact verification of multilingual short-video news; Design Science Research. Check languages covered (tie-break 2).
A7: 6 | B7: Provenance-driven nanopublications: representing source lineage and trust networks for multi-source assertions | C7: Exclude | D7: E3 | F7: Nanopublication provenance model; no LLM component.
A8: 7 | B8: An LLM-based multi-agent system for patient discharge assessment | C8: Maybe | E8: 2 | F8: LLM multi-agent with claim-level verification, but inputs are structured EHR fields (I6 risk).
A9: 8 | B9: Hallucination to truth: a review of fact-checking and factuality evaluation in large language models | C9: Exclude | D9: E4 | F9: Literature review, not a multi-agent architecture.
A10: 9 | B10: FARM: A Multi-Agent Framework for Automated Construction of Multi-Species Livestock Health Knowledge Graphs | C10: Include | E10: 2 | F10: Multi-agent LLM zero-shot extraction from unstructured literature (livestock health).
A11: 10 | B11: Insider Threat Detection and Evidence-Grounded Triage Using a Heterogeneous Dual-Branch Network and a Constrained LLM Agent | C11: Exclude | D11: E4 | F11: Dual-branch anomaly detector plus one constrained LLM agent over behavioral logs; no multi-agent architecture.
A12: 11 | B12: An automatic modeling method for rough discrete fracture networks based on LLM Agent; [基于LLM Agent的粗糙离散裂隙网络自动建模方法] | C12: Exclude | D12: E2 | F12: Original-document language is Chinese (Scopus metadata).
A13: 12 | B13: Semantic Information Extraction and Multi-Agent Communication Optimization Based on Generative Pre-Trained Transformer | C13: Exclude | D13: E6 | F13: Agents exchange observations to optimise communication in a multi-agent system (reinforcement learning appears in the author keywords, not in the abstract); the LLM extracts semantic information from observation data, not from text documents or claims.
A14: 13 | B14: DelphiAgent: A trustworthy multi-agent verification framework for automated fact verification | C14: Include | E14: 2 | F14: Multi-LLM Delphi-style framework for fact verification; evidence mining from reports; transparency focus (tie-break 3).
A15: 14 | B15: From LLMs to sustainable proteins: fine-tuning and prompt engineering for multi-agent AI in waste carbon-utilising microbial protein production | C15: Include | E15: 2 | F15: Two LLM agents (literature search, information extraction) on scientific literature.
A16: 15 | B16: Debating to verify: A robust and explainable multi-agent LLM system for fact-checking | C16: Include | E16: 2 | F16: Multi-agent debate for fact verification; Vietnamese and multilingual X-Fact benchmarks (tie-break 2).
A17: 16 | B17: Automated building energy modeling for energy retrofits using a large language model-based multi-agent framework | C17: Exclude | D17: E5 | F17: Primary task is generating/calibrating energy models from drawings, specs and sensor data; extraction is an intermediate step.
A18: 17 | B18: Unsupervised column relevance extraction for table-based fact verification via structured and explainable large language model reasoning | C18: Exclude | D18: E4 | F18: Single zero-shot framework for table-based verification; abstract contrasts itself with multi-agent pipelines (tabular data, I6 also at risk).
A19: 18 | B19: Mitigating Hallucinations in Finance-Based Multi-Agent Large Language Model Systems | C19: Exclude | D19: E4 | F19: Six-signal hallucination detector; abstract describes no interacting agents with distinct roles. LOW CONFIDENCE - verify.
A20: 19 | B20: The perils and promises of fact-checking with large language models | C20: Maybe | E20: 2 | F20: LLM agents that phrase queries, retrieve, decide and cite sources; includes low-resource languages. Check I4 (one agent vs several).
A21: 20 | B21: CoAgt: unleashing the reasoning capabilities of large language models on tabular data with a chain of agents | C21: Exclude | D21: E6 | F21: Table reasoning over tabular data.
A22: 21 | B22: LLM-based AI agents for automated extraction of material properties and structural features | C22: Include | E22: 2 | F22: Multi-agent orchestration with LLM-judge for extraction from ~10,000 full-text articles.
A23: 22 | B23: Automatic building energy model development and debugging using large language models agentic workflow | C23: Exclude | D23: E5 | F23: Generates and debugs building energy models; extraction is a sub-step.
A24: 23 | B24: Agent-based multimodal information extraction for nanomaterials | C24: Include | E24: 2 | F24: Multi-agent extraction from scientific articles (text plus figures).
A25: 24 | B25: Multi-source assembly knowledge fusion and assembly agent for robotic assembly; [基于多源装配知识融合与装配智能体的机器人装配方法] | C25: Exclude | D25: E5 | F25: Robot assembly planning and code generation.
A26: 25 | B26: ARE TWO MINDS BETTER THAN ONE? EVALUATING COLLABORATIVE REASONING IN LLMS | C26: Exclude | D26: E1 | F26: No DOI in Scopus record.
A27: 26 | B27: Debapt: Ontology-driven multi-agent debate for APT adversary profile construction from cyber threat intelligence | C27: Include | E27: 2 | F27: Ontology-driven multi-agent debate for information extraction from cyber threat intelligence reports.
A28: 27 | B28: Improved multi-agent knowledge sharing system using knowledge graphs for news bias detection and fact-checking | C28: Include | E28: 2 | F28: Multi-agent LLM system with shared knowledge graph for news bias detection and fact-checking.
A29: 28 | B29: Research on risk decision-making generation method for water conservancy project based on multimodal knowledge graph and large language model | C29: Exclude | D29: E5 | F29: Risk decision generation; entity extraction uses BERT-BiLSTM-CRF (not LLM).
A30: 29 | B30: T2F: a domain-agnostic multi-agent framework for unstructured text to factuality evaluation items generation | C30: Include | E30: 2 | F30: Multi-agent (information extraction and validation agents) but output is factuality-evaluation item generation; check I5. REVISED to Include after second review: I5 is met by the information-extraction agent; generating evaluation items does not exclude it.
A31: 30 | B31: From weak signals to risk indicators: An LLM-based information extraction architecture for IT project risk management | C31: Include | E31: 2 | F31: Design Science; LLM multi-agent IE architecture with evidence-linked indicators and extraction control (traceability).
A32: 31 | B32: MRBalance: A framework for enhancing event causality identification in multi-agent debates via role assignment | C32: Include | E32: 2 | F32: Role-based multi-agent debate for event causality identification (information extraction).
A33: 32 | B33: Tool-MAD: A Multi-Agent Debate Framework for Fact Verification with Diverse Tool Augmentation and Adaptive Retrieval | C33: Include | E33: 2 | F33: Multi-agent debate with tool-augmented agents for fact verification.
A34: 33 | B34: RCRQ: Multi-agent Information Extraction Framework for Traffic Accident Texts; [RCRQ:面向交通事故文本的多智能体信息抽取框架] | C34: Include | E34: 1 | F34: TIER 1 CANDIDATE: multi-agent IE on police/administrative traffic-accident reports. Verify full-text language (Chinese-language journal) and document type.
A35: 34 | B35: FactualRAG: a RAG-Powered framework for LLM fact-checking via IFCN-Accredited sources | C35: Include | E35: 2 | F35: RAG fact-checking with IFCN sources; multi-agent debate is an extension. Check I4; journalism/policy orientation. REVISED to Include after second review: criteria do not require the multi-agent design to be the paper's only architecture.
A36: 35 | B36: Fact or Fake? Assessing the Role of Deepfake Detectors in Multimodal Misinformation Detection | C36: Include | E36: 2 | F36: Multimodal misinformation; multi-agent debate is one of several systems analysed. Check I4/I6. REVISED to Include after second review: I6 excludes only non-text-only input, not multimodal input that includes text claims.
A37: 36 | B37: A more advanced group polarization measurement approach based on LLM-based agents and graphs | C37: Include | E37: 2 | F37: LLM multi-agent zero-shot stance detection on social media text. Source is an iConference issue of Information Research - check source type.
A38: 37 | B38: NLP System for Automation of Document Workflow in a Research and Development Organization—A Case Study | C38: Include | E38: 1 | F38: TIER 1 CANDIDATE: multi-agent classification and extraction for administrative and scientific documents of a national research institute.
A39: 38 | B39: LLM-IE: a python package for biomedical generative information extraction with large language models | C39: Exclude | D39: E4 | F39: Python package with a single interactive LLM agent for schema design; no multi-agent architecture.
A40: 39 | B40: Multi-agent systems and credibility-based advanced scoring mechanism in fact-checking | C40: Include | E40: 2 | F40: Multi-agent fact-checking with per-agent information sources and credibility scoring.
A41: 40 | B41: Development and validation of a multi-agent AI pipeline for automated credibility assessment of tobacco misinformation: a proof-of-concept study | C41: Include | E41: 2 | F41: Three-agent pipeline for claim credibility (tobacco misinformation) validated against experts.
A42: 41 | B42: Self-improving multi-agent framework for zero-shot multimodal information extraction | C42: Include | E42: 2 | F42: Multi-agent zero-shot multimodal IE; text is part of the input.
A43: 42 | B43: Guided and knowledgeable multi-agent debate for fact verification | C43: Include | E43: 2 | F43: Guided multi-agent debate with external knowledge for fact verification.
A44: 43 | B44: Enhancing global value chain transparency: A multi-agent AI framework for detecting ESG greenwashing with open-source innovations | C44: Include | E44: 1 | F44: TIER 1 CANDIDATE: multi-agent comparison of corporate ESG disclosures with news and regulatory records (verification).
A45: 44 | B45: LLMs for knowledge graph construction and reasoning: recent capabilities and future opportunities | C45: Exclude | D45: E4 | F45: Evaluation of single LLMs for knowledge-graph construction; no multi-agent design.

Sheet Validation
A1: Human validation of AI screening
A2: Records screened by AI (all) | B2: =COUNTA('Screening (human)'!A2:A45) -> 44
A3: Minimum human-validated (10% rule) | B3: =ROUNDUP(0.1*B2,0) -> 5
A4: Records in human validation sample | B4: =COUNTIF('Screening (human)'!T2:T45,"Y") -> 6
A5: Sample checked so far | B5: =COUNTIF('Screening (human)'!U2:U45,"Agree")+COUNTIF('Screening (human)'!U2:U45,"Disagree") -> 0
A6: Agree | B6: =COUNTIF('Screening (human)'!U2:U45,"Agree") -> 0
A7: Disagree | B7: =COUNTIF('Screening (human)'!U2:U45,"Disagree") -> 0
A8: Human-AI agreement on sample | B8: =IF(B5=0,"",B6/B5)
A9: 10% rule met? | B9: =IF(AND(B4>=B3,B5=B4),"OK","CHECK: complete column U") -> CHECK: complete column U
A11: Sample = 5 records drawn at random with Python random.Random(seed 20261024) from IDs 1-44, plus record 18, which the AI flagged as low confidence. Disagreements are resolved in favour of the human reviewer. Cohen's kappa is not reported: the AI was the primary screener, not an independent second reviewer.

Sheet PRISMA numbers
A1: PRISMA 2020 box | B1: n | C1: How it is computed / note
A2: IDENTIFICATION
A3: Records identified from databases (Scopus) | B3: =COUNTA('Screening (human)'!A2:A45) -> 44 | C3: Final search, iteration 3 (see Search log)
A4: Records removed before screening: duplicates | B4: 0 | C4: Single database; typed input
A5: Records removed before screening: marked ineligible by automation tools | B5: 0 | C5: None used; typed input
A6: Records removed before screening: other reasons | B6: 0 | C6: None; typed input
A7: SCREENING (title/abstract)
A8: Records screened | B8: =B3-B4-B5-B6 -> 44 | C8: Identified minus removed
A9: Screening exclusion E1: not journal article / no DOI | B9: =COUNTIFS('Screening (human)'!I2:I45,"Exclude",'Screening (human)'!J2:J45,"E1") -> 1
A10: Screening exclusion E2: language | B10: =COUNTIFS('Screening (human)'!I2:I45,"Exclude",'Screening (human)'!J2:J45,"E2") -> 1
A11: Screening exclusion E3: not LLM-based | B11: =COUNTIFS('Screening (human)'!I2:I45,"Exclude",'Screening (human)'!J2:J45,"E3") -> 1
A12: Screening exclusion E4: not multi-agent | B12: =COUNTIFS('Screening (human)'!I2:I45,"Exclude",'Screening (human)'!J2:J45,"E4") -> 6
A13: Screening exclusion E5: no extraction/classification/verification | B13: =COUNTIFS('Screening (human)'!I2:I45,"Exclude",'Screening (human)'!J2:J45,"E5") -> 4
A14: Screening exclusion E6: out of domain | B14: =COUNTIFS('Screening (human)'!I2:I45,"Exclude",'Screening (human)'!J2:J45,"E6") -> 2
A15: Screening exclusion E9: eligible by abstract, not assessed (prioritised-reading cut) | B15: =COUNTIFS('Screening (human)'!V2:V45,"Y",'Screening (human)'!I2:I45,"<>Exclude") -> 0 | C15: Declared deviation: full text assessed in fixed priority order (see Reading order)
A16: Records excluded at screening (total) | B16: =SUM(B9:B15) -> 15 | C16: PRISMA box 'Records excluded'
A17: Reports sought for retrieval | B17: =B8-B16 -> 29 | C17: Screened minus excluded
A18: Reports not retrieved | B18: =COUNTIF('Screening (human)'!K2:K45,"Not retrieved") -> 0 | C18: Full-text decision = Not retrieved (E7)
A19: ELIGIBILITY (full text)
A20: Reports assessed for eligibility | B20: =B17-B18 -> 29 | C20: Sought minus not retrieved
A21: Full-text exclusion E1 | B21: =COUNTIFS('Screening (human)'!K2:K45,"Exclude",'Screening (human)'!L2:L45,"E1") -> 0
A22: Full-text exclusion E2 language | B22: =COUNTIFS('Screening (human)'!K2:K45,"Exclude",'Screening (human)'!L2:L45,"E2") -> 0
A23: Full-text exclusion E3 not LLM-based | B23: =COUNTIFS('Screening (human)'!K2:K45,"Exclude",'Screening (human)'!L2:L45,"E3") -> 0
A24: Full-text exclusion E4 not multi-agent | B24: =COUNTIFS('Screening (human)'!K2:K45,"Exclude",'Screening (human)'!L2:L45,"E4") -> 0
A25: Full-text exclusion E5 no task | B25: =COUNTIFS('Screening (human)'!K2:K45,"Exclude",'Screening (human)'!L2:L45,"E5") -> 0
A26: Full-text exclusion E6 out of domain | B26: =COUNTIFS('Screening (human)'!K2:K45,"Exclude",'Screening (human)'!L2:L45,"E6") -> 0
A27: Full-text exclusion E8 duplicate | B27: =COUNTIFS('Screening (human)'!K2:K45,"Exclude",'Screening (human)'!L2:L45,"E8") -> 0
A28: Full-text exclusion E9: eligible, not selected (tie-break cut to 10) | B28: =COUNTIFS('Screening (human)'!K2:K45,"Eligible",'Screening (human)'!R2:R45,"No") -> 0 | C28: Explicit step from eligible to final 10
A29: Total reports excluded at full text | B29: =SUM(B21:B28) -> 0
A30: INCLUDED
A31: Studies included in review | B31: =COUNTIF('Screening (human)'!R2:R45,"Yes") -> 0 | C31: Selected in top 10 = Yes
A32: CHECKS (all must say OK)
A33: Title/abstract decisions completed | B33: =IF(COUNTA('Screening (human)'!I2:I45)=B3,"OK","CHECK: "&(B3-COUNTA('Screening (human)'!I2:I45))&" pending") -> OK
A34: Every screening exclusion has a reason code | B34: =IF(COUNTIFS('Screening (human)'!I2:I45,"Exclude",'Screening (human)'!J2:J45,"")=0,"OK","CHECK") -> OK
A35: Every full-text exclusion has a reason code | B35: =IF(COUNTIFS('Screening (human)'!K2:K45,"Exclude",'Screening (human)'!L2:L45,"")=0,"OK","CHECK") -> OK
A36: Records marked Y in column V were not read (K empty) | B36: =IF(COUNTIFS('Screening (human)'!V2:V45,"Y",'Screening (human)'!K2:K45,"<>")=0,"OK","CHECK: column V and K both filled") -> OK
A37: No record is still pending full text | B37: =IF(B20=COUNTIF('Screening (human)'!K2:K45,"Eligible")+COUNTIF('Screening (human)'!K2:K45,"Exclude"),"OK","CHECK: "&(B20-COUNTIF('Screening (human)'!K2:K45,"Eligible")-COUNTIF('Screening (human)'!K2:K45,"Exclude"))&" sought but not yet decided") -> CHECK: 28 sought but not yet decided | C37: Every sought report needs Eligible / Exclude / Not retrieved
A38: Assessed - excluded = included | B38: =IF(B20-B29=B31,"OK","CHECK") -> CHECK | C38: Numbers must add up
A39: Whole funnel adds up | B39: =IF(B3-B4-B5-B6-B16-B18-B29=B31,"OK","CHECK") -> CHECK | C39: Identified - removed - excluded - not retrieved - excluded(FT) = included
A40: Included equals 10 | B40: =IF(B31=10,"OK","CHECK: "&B31) -> CHECK: 0 | C40: Deliverable requires 10 papers

Sheet Reading order
A1: Order | B1: ID | C1: Group | D1: First author | E1: Year | F1: Title | G1: DOI | H1: Check at full text | I1: Done (Y)
A2: 1 | B2: 33 | C2: A | D2: SHI D. | E2: 2026 | F2: RCRQ: Multi-agent Information Extraction Framework for Traffic Accident Texts; [RCRQ:面向交通事故文本的多智能体信息抽取框架] | G2: 10.3778/j.issn.1673-9418.2508069 | H2: Tier 1 candidates: full-text language (I2) and document types.
A3: 2 | B3: 37 | C3: A | D3: Iwaszenko S. | E3: 2026 | F3: NLP System for Automation of Document Workflow in a Research and Development Organization—A Case Study | G3: 10.3390/app16094562 | H3: Tier 1 candidates: full-text language (I2) and document types.
A4: 3 | B4: 43 | C4: A | D4: Song X. | E4: 2026 | F4: Enhancing global value chain transparency: A multi-agent AI framework for detecting ESG greenwashing with open-source innovations | G4: 10.1016/j.jbusres.2026.116242 | H4: Tier 1 candidates: full-text language (I2) and document types.
A5: 4 | B5: 15 | C5: B | D5: Nguyen T.-A. | E5: 2026 | F5: Debating to verify: A robust and explainable multi-agent LLM system for fact-checking | G5: 10.1016/j.icte.2026.05.017 | H5: Tie-break contenders (context, traceability/governance): I2 language, I3 LLM, I4 interacting agents with distinct roles, I5 task on text.
A6: 5 | B6: 19 | C6: B | D6: Quelle D. | E6: 2024 | F6: The perils and promises of fact-checking with large language models | G6: 10.3389/frai.2024.1341697 | H6: Tie-break contenders (context, traceability/governance): I2 language, I3 LLM, I4 interacting agents with distinct roles, I5 task on text.
A7: 6 | B7: 13 | C7: B | D7: Xiong C. | E7: 2025 | F7: DelphiAgent: A trustworthy multi-agent verification framework for automated fact verification | G7: 10.1016/j.ipm.2025.104241 | H7: Tie-break contenders (context, traceability/governance): I2 language, I3 LLM, I4 interacting agents with distinct roles, I5 task on text.
A8: 7 | B8: 30 | C8: B | D8: Paetzold F. | E8: 2026 | F8: From weak signals to risk indicators: An LLM-based information extraction architecture for IT project risk management | G8: 10.1007/s12525-026-00928-6 | H8: Tie-break contenders (context, traceability/governance): I2 language, I3 LLM, I4 interacting agents with distinct roles, I5 task on text.
A9: 8 | B9: 40 | C9: B | D9: Elmitwalli S. | E9: 2025 | F9: Development and validation of a multi-agent AI pipeline for automated credibility assessment of tobacco misinformation: a proof-of-concept study | G9: 10.3389/frai.2025.1659861 | H9: Tie-break contenders (context, traceability/governance): I2 language, I3 LLM, I4 interacting agents with distinct roles, I5 task on text.
A10: 9 | B10: 39 | C10: B | D10: Dong Y. | E10: 2026 | F10: Multi-agent systems and credibility-based advanced scoring mechanism in fact-checking | G10: 10.1038/s41598-026-41862-z | H10: Tie-break contenders (context, traceability/governance): I2 language, I3 LLM, I4 interacting agents with distinct roles, I5 task on text.
A11: 10 | B11: 5 | C11: B | D11: Lian X. | E11: 2026 | F11: An LLM-based Fact-Checking Approach for Multilingual Fake News Detection in Short-Form Video News | G11: 10.1007/s10796-026-10755-x | H11: Tie-break contenders (context, traceability/governance): I2 language, I3 LLM, I4 interacting agents with distinct roles, I5 task on text.
A12: 11 | B12: 7 | C12: B | D12: Gebreab S. | E12: 2026 | F12: An LLM-based multi-agent system for patient discharge assessment | G12: 10.1016/j.cmpbup.2026.100261 | H12: Tie-break contenders (context, traceability/governance): I2 language, I3 LLM, I4 interacting agents with distinct roles, I5 task on text.
A13: 12 | B13: 34 | C13: B | D13: Chang L.-J. | E13: 2026 | F13: FactualRAG: a RAG-Powered framework for LLM fact-checking via IFCN-Accredited sources | G13: 10.1007/s10844-026-01041-y | H13: Tie-break contenders (context, traceability/governance): I2 language, I3 LLM, I4 interacting agents with distinct roles, I5 task on text.
... A31: 30 | B31: 35 | C31: D | D31: Sharifuzzaman Sagar A.S.M. | E31: 2026 | F31: Fact or Fake? Assessing the Role of Deepfake Detectors in Multimodal Misinformation Detection | G31: 10.1109/ACCESS.2026.3686437 | H31: Doubtful records, read only if still needed: the specific question from the screening note (I4/I5/I6).
A33: Rule: assess full texts in this fixed order. Stop when 10 papers are confirmed eligible (and all of group A and B have been assessed). Every unread record that was Include/Maybe at screening gets Y in column V of 'Screening (human)' (code E9, not assessed). This is a declared deviation adopted on 24 October 2026 because of the delivery deadline; it is reported as a limitation.

Sheet Evidence verification
A1: ID | B1: First author | C1: Year | D1: Title | E1: DOI | F1: Full text opened by Mayte (Y/N) | G1: Full-text language | H1: LLM(s) named in Methods | I1: Agents and their roles (as in the paper) | J1: Task on text (extract / classify / verify) and input documents | K1: Verbatim passage (max 2 lines, copied from the PDF) | L1: Page / section of the passage | M1: Date verified
A2: 37 | B2: Iwaszenko S. | C2: 2026 | D2: NLP System for Automation of Document Workflow in a Research and Development Organization—A Case Study | E2: 10.3390/app16094562
A3: 30 | B3: Paetzold F. | C3: 2026 | D3: From weak signals to risk indicators: An LLM-based information extraction architecture for IT project risk management | E3: 10.1007/s12525-026-00928-6
A4: 7 | B4: Gebreab S. | C4: 2026 | D4: An LLM-based multi-agent system for patient discharge assessment | E4: 10.1016/j.cmpbup.2026.100261
A5: 15 | B5: Nguyen T.-A. | C5: 2026 | D5: Debating to verify: A robust and explainable multi-agent LLM system for fact-checking | E5: 10.1016/j.icte.2026.05.017
A6: 5 | B6: Lian X. | C6: 2026 | D6: An LLM-based Fact-Checking Approach for Multilingual Fake News Detection in Short-Form Video News | E6: 10.1007/s10796-026-10755-x
A7: 34 | B7: Chang L.-J. | C7: 2026 | D7: FactualRAG: a RAG-Powered framework for LLM fact-checking via IFCN-Accredited sources | E7: 10.1007/s10844-026-01041-y
A8: 39 | B8: Dong Y. | C8: 2026 | D8: Multi-agent systems and credibility-based advanced scoring mechanism in fact-checking | E8: 10.1038/s41598-026-41862-z
A9: 42 | B9: Ma X. | C9: 2026 | D9: Guided and knowledgeable multi-agent debate for fact verification | E9: 10.1016/j.eswa.2025.130103
A10: 13 | B10: Xiong C. | C10: 2025 | D10: DelphiAgent: A trustworthy multi-agent verification framework for automated fact verification | E10: 10.1016/j.ipm.2025.104241
A11: 40 | B11: Elmitwalli S. | C11: 2025 | D11: Development and validation of a multi-agent AI pipeline for automated credibility assessment of tobacco misinformation: a proof-of-concept study | E11: 10.3389/frai.2025.1659861
A12: 4 | B12: Pu J. | C12: 2026 | D12: MA-APKG: A multi-agent LLM-based method for construction aviation product assembly process knowledge graph | E12: 10.1016/j.jmsy.2026.04.031
A13: 19 | B13: Quelle D. | C13: 2024 | D13: The perils and promises of fact-checking with large language models | E13: 10.3389/frai.2024.1341697
A14: 2 | B14: Gorshenin A.K. | C14: 2025 | D14: A Multiagent Multimodal Neural Architecture with Probabilistic Evidence Aggregation for Detecting Fake Messages | E14: 10.1134/S1054661825700543
A16: Rule: a record may be marked Eligible (column K) only if column F = Y and columns G-L are filled from the paper itself. Quotes must be copied from the PDF, not paraphrased or reconstructed. If the full text was not opened, K must stay empty (or Not retrieved), and the record cannot be one of the 10.

Sheet Full-text notes
A1: ID | B1: Review basis / access | C1: Full-text language | D1: Document types | E1: Decision / qualification | F1: Source / location
A2: 37 | B2: Publisher article body inspected; eligibility accepted by Mayte | C2: English | D2: Invoices; contracts; scientific articles; tender specifications; plagiarism reports; ISO procedures. | E2: K=Eligible; M=1 (numeric Tier 1 for existing formulas); N=N; O=Y. Institutional confidential documents, not a public-access corpus. Governance explicitly addresses permitted tools, prohibited data categories, authorizations, responsibilities and human approval. Governance discussion does not establish measured governance effectiveness. | F2: https://doi.org/10.3390/app16094562 ; sections 2.3, 3.1, 3.2; AI-use regulation discussion; Data Availability Statement.
A3: 33 | B3: Publisher unavailable; catalogue abstract only; PDF not recovered | C3: Unverified; do not infer from bilingual title/abstract | D3: Autonomous-vehicle accident texts (abstract only). Exact source genres unverified. | E3: K/L unchanged. E2 requires confirmation of full-text language. | F3: https://fcst.ceaj.org/CN/10.3778/j.issn.1673-9418.2508069 ; https://opaj.napstic.cn/periodicalArticle/0120260501898998
A4: 43 | B4: Publisher access blocked; no accessible full-text copy found | C4: Unverified from full text | D4: Corporate ESG disclosures contrasted with negative news and regulatory records (abstract only). | E4: K/L unchanged pending the user deadline: 24 October 2026, 21:00 America/Lima. If still not retrieved then, K=Not retrieved; L=E7. | F4: https://doi.org/10.1016/j.jbusres.2026.116242
A5: 15 | B5: Publisher abstract retrieved; article marked open access, corrected proof; body/PDF not recovered | C5: Not yet verified from article body | D5: Textual claim verification on ViFactCheck, X-Fact and FEVER; precise evidence inputs require full text. | E5: No full-text eligibility entered. Benchmark languages must not be confused with article language. | F5: https://doi.org/10.1016/j.icte.2026.05.017
A6: 13 | B6: Publisher abstract and author code repository inspected; article PDF not recovered | C6: Not yet verified from article body | D6: Claims and raw reports used as evidence; RAWFC and LIAR-RAW benchmarks. | E6: No full-text eligibility entered. The author repository supports architecture details but is not a replacement for the published article. | F6: https://doi.org/10.1016/j.ipm.2025.104241 ; https://github.com/zjfgh2015/DelphiAgent
A7: 30 | B7: Publisher full-text HTML inspected | C7: English | D7: Project communication: emails, meeting minutes, issue trackers; architecture also admits external reports and cybersecurity alerts. Technical evaluation uses 150 synthetic case-grounded documents. | E7: AI recommendation: eligible under I1-I6; not entered as a human decision. Explicit evidence/provenance links and governance discussion. Quantitative results do not demonstrate generalizability to authentic communication. Tier requires consistent treatment of internal project administration. | F7: https://doi.org/10.1007/s12525-026-00928-6 ; Input Layer, Technical implementation, Technical evaluation, Discussion.

Sheet Gap candidates
A1: Gap type | B1: Candidate gap (reviewer inference) | C1: Evidence from included/candidate article | D1: Scope qualification | E1: Citation / locator
A2: Methodological | B2: Evaluate extraction accuracy across administrative and legal document categories, not only scientific articles. | C2: Classification covers six document categories; quantitative extraction evaluation focuses on the Scientific Article pipeline. | D2: ID 37: Tier 1 by administrative/legal content; institutional confidential documents, not public-access documents. This is a limitation of this study, not proof of a field-wide absence. | E2: Iwaszenko et al. (2026), sections 3.1-3.2. https://doi.org/10.3390/app16094562
A3: Contextual | B3: Test transfer to public-access Peruvian documents in Spanish. | C3: The study uses institutional R&D workflows and confidential operational documents. | D3: ID 37 supports a transfer question; it does not establish that no other study addresses Peru or Spanish. | E3: Iwaszenko et al. (2026), section 3.1 and Data Availability Statement. https://doi.org/10.3390/app16094562
A4: Methodological | B4: Validate extraction and provenance performance on authentic project/document corpora after controlled synthetic evaluation. | C4: Technical evaluation uses 150 synthetic case-grounded documents; the authors explicitly limit generalizability. | D4: ID 30 remains an AI-reviewed candidate; do not treat this row as a final synthesis inclusion. | E4: Paetzold et al. (2026), Technical evaluation and Discussion. https://doi.org/10.1007/s12525-026-00928-6
